[
  {
    "home": "Spain",
    "away": "Curaçao",
    "homeELO": 2031.1,
    "awayELO": 1597.2,
    "expectedGoals": "4.13 - 0.31",
    "probability_1": 94.1,
    "probability_X": 4.8,
    "probability_2": 1.1,
    "confidence": 94.1,
    "prediction": "1",
    "prode": "1",
    "eloAdvantage": 4.34
  },
  {
    "home": "Argentina",
    "away": "Curaçao",
    "homeELO": 1991.6,
    "awayELO": 1597.2,
    "expectedGoals": "3.38 - 0.24",
    "probability_1": 93.2,
    "probability_X": 5.5,
    "probability_2": 1.4,
    "confidence": 93.2,
    "prediction": "1",
    "prode": "1",
    "eloAdvantage": 3.945
  },
  {
    "home": "France",
    "away": "Curaçao",
    "homeELO": 1964.8,
    "awayELO": 1597.2,
    "expectedGoals": "3.46 - 0.35",
    "probability_1": 91.3,
    "probability_X": 6.5,
    "probability_2": 2.2,
    "confidence": 91.3,
    "prediction": "1",
    "prode": "1",
    "eloAdvantage": 3.676
  },
  {
    "home": "Portugal",
    "away": "Curaçao",
    "homeELO": 1902.8,
    "awayELO": 1597.2,
    "expectedGoals": "3.61 - 0.36",
    "probability_1": 90.9,
    "probability_X": 6.6,
    "probability_2": 2.6,
    "confidence": 90.9,
    "prediction": "1",
    "prode": "1",
    "eloAdvantage": 3.056
  },
  {
    "home": "England",
    "away": "Curaçao",
    "homeELO": 1938.1,
    "awayELO": 1597.2,
    "expectedGoals": "3.25 - 0.27",
    "probability_1": 90.8,
    "probability_X": 7.2,
    "probability_2": 2.0,
    "confidence": 90.8,
    "prediction": "1",
    "prode": "1",
    "eloAdvantage": 3.41
  },
  {
    "home": "Brazil",
    "away": "Curaçao",
    "homeELO": 1906.3,
    "awayELO": 1597.2,
    "expectedGoals": "3.63 - 0.33",
    "probability_1": 90.8,
    "probability_X": 6.5,
    "probability_2": 2.7,
    "confidence": 90.8,
    "prediction": "1",
    "prode": "1",
    "eloAdvantage": 3.091
  },
  {
    "home": "Germany",
    "away": "Curaçao",
    "homeELO": 1878.7,
    "awayELO": 1597.2,
    "expectedGoals": "3.81 - 0.45",
    "probability_1": 90.8,
    "probability_X": 6.1,
    "probability_2": 3.2,
    "confidence": 90.8,
    "prediction": "1",
    "prode": "1",
    "eloAdvantage": 2.815
  },
  {
    "home": "Spain",
    "away": "Qatar",
    "homeELO": 2031.1,
    "awayELO": 1589.8,
    "expectedGoals": "3.34 - 0.44",
    "probability_1": 89.5,
    "probability_X": 8.6,
    "probability_2": 1.9,
    "confidence": 89.5,
    "prediction": "1",
    "prode": "1",
    "eloAdvantage": 4.413
  },
  {
    "home": "Colombia",
    "away": "Curaçao",
    "homeELO": 1885.6,
    "awayELO": 1597.2,
    "expectedGoals": "3.17 - 0.37",
    "probability_1": 88.8,
    "probability_X": 8.0,
    "probability_2": 3.2,
    "confidence": 88.8,
    "prediction": "1",
    "prode": "1",
    "eloAdvantage": 2.884
  },
  {
    "home": "Netherlands",
    "away": "Curaçao",
    "homeELO": 1866.5,
    "awayELO": 1597.2,
    "expectedGoals": "3.49 - 0.42",
    "probability_1": 88.6,
    "probability_X": 8.0,
    "probability_2": 3.4,
    "confidence": 88.6,
    "prediction": "1",
    "prode": "1",
    "eloAdvantage": 2.693
  },
  {
    "home": "Belgium",
    "away": "Curaçao",
    "homeELO": 1806.1,
    "awayELO": 1597.2,
    "expectedGoals": "3.26 - 0.40",
    "probability_1": 88.0,
    "probability_X": 7.9,
    "probability_2": 4.1,
    "confidence": 88.0,
    "prediction": "1",
    "prode": "1",
    "eloAdvantage": 2.089
  },
  {
    "home": "Argentina",
    "away": "Qatar",
    "homeELO": 1991.6,
    "awayELO": 1589.8,
    "expectedGoals": "2.74 - 0.34",
    "probability_1": 87.7,
    "probability_X": 9.9,
    "probability_2": 2.3,
    "confidence": 87.7,
    "prediction": "1",
    "prode": "1",
    "eloAdvantage": 4.018
  },
  {
    "home": "Spain",
    "away": "Haiti",
    "homeELO": 2031.1,
    "awayELO": 1673.3,
    "expectedGoals": "3.53 - 0.41",
    "probability_1": 87.5,
    "probability_X": 9.7,
    "probability_2": 2.8,
    "confidence": 87.5,
    "prediction": "1",
    "prode": "1",
    "eloAdvantage": 3.578
  },
  {
    "home": "Morocco",
    "away": "Curaçao",
    "homeELO": 1950.5,
    "awayELO": 1597.2,
    "expectedGoals": "2.31 - 0.27",
    "probability_1": 87.3,
    "probability_X": 10.2,
    "probability_2": 2.5,
    "confidence": 87.3,
    "prediction": "1",
    "prode": "1",
    "eloAdvantage": 3.534
  },
  {
    "home": "Spain",
    "away": "Cabo Verde",
    "homeELO": 2031.1,
    "awayELO": 1614.3,
    "expectedGoals": "2.60 - 0.37",
    "probability_1": 87.1,
    "probability_X": 10.5,
    "probability_2": 2.4,
    "confidence": 87.1,
    "prediction": "1",
    "prode": "1",
    "eloAdvantage": 4.168
  },
  {
    "home": "Japan",
    "away": "Curaçao",
    "homeELO": 1923.1,
    "awayELO": 1597.2,
    "expectedGoals": "2.70 - 0.39",
    "probability_1": 87.0,
    "probability_X": 9.9,
    "probability_2": 3.1,
    "confidence": 87.0,
    "prediction": "1",
    "prode": "1",
    "eloAdvantage": 3.259
  },
  {
    "home": "Norway",
    "away": "Curaçao",
    "homeELO": 1837.3,
    "awayELO": 1597.2,
    "expectedGoals": "3.10 - 0.45",
    "probability_1": 86.8,
    "probability_X": 9.2,
    "probability_2": 4.0,
    "confidence": 86.8,
    "prediction": "1",
    "prode": "1",
    "eloAdvantage": 2.402
  },
  {
    "home": "Spain",
    "away": "Ghana",
    "homeELO": 2031.1,
    "awayELO": 1587.4,
    "expectedGoals": "2.47 - 0.43",
    "probability_1": 86.2,
    "probability_X": 11.1,
    "probability_2": 2.7,
    "confidence": 86.2,
    "prediction": "1",
    "prode": "1",
    "eloAdvantage": 4.438
  },
  {
    "home": "Spain",
    "away": "Bosnia and Herzegovina",
    "homeELO": 2031.1,
    "awayELO": 1550.2,
    "expectedGoals": "2.42 - 0.43",
    "probability_1": 86.1,
    "probability_X": 11.4,
    "probability_2": 2.5,
    "confidence": 86.1,
    "prediction": "1",
    "prode": "1",
    "eloAdvantage": 4.809
  },
  {
    "home": "Argentina",
    "away": "Haiti",
    "homeELO": 1991.6,
    "awayELO": 1673.3,
    "expectedGoals": "2.89 - 0.32",
    "probability_1": 85.9,
    "probability_X": 10.7,
    "probability_2": 3.4,
    "confidence": 85.9,
    "prediction": "1",
    "prode": "1",
    "eloAdvantage": 3.183
  },
  {
    "home": "Brazil",
    "away": "Qatar",
    "homeELO": 1906.3,
    "awayELO": 1589.8,
    "expectedGoals": "2.94 - 0.47",
    "probability_1": 85.4,
    "probability_X": 10.7,
    "probability_2": 3.9,
    "confidence": 85.4,
    "prediction": "1",
    "prode": "1",
    "eloAdvantage": 3.165
  },
  {
    "home": "Portugal",
    "away": "Qatar",
    "homeELO": 1902.8,
    "awayELO": 1589.8,
    "expectedGoals": "2.92 - 0.51",
    "probability_1": 85.3,
    "probability_X": 11.0,
    "probability_2": 3.8,
    "confidence": 85.3,
    "prediction": "1",
    "prode": "1",
    "eloAdvantage": 3.129
  },
  {
    "home": "Spain",
    "away": "New Zealand",
    "homeELO": 2031.1,
    "awayELO": 1669.9,
    "expectedGoals": "2.44 - 0.34",
    "probability_1": 85.2,
    "probability_X": 11.9,
    "probability_2": 3.0,
    "confidence": 85.2,
    "prediction": "1",
    "prode": "1",
    "eloAdvantage": 3.612
  },
  {
    "home": "France",
    "away": "Qatar",
    "homeELO": 1964.8,
    "awayELO": 1589.8,
    "expectedGoals": "2.80 - 0.49",
    "probability_1": 84.7,
    "probability_X": 11.6,
    "probability_2": 3.7,
    "confidence": 84.7,
    "prediction": "1",
    "prode": "1",
    "eloAdvantage": 3.75
  },
  {
    "home": "Spain",
    "away": "Jordan",
    "homeELO": 2031.1,
    "awayELO": 1750.0,
    "expectedGoals": "2.73 - 0.49",
    "probability_1": 84.4,
    "probability_X": 11.4,
    "probability_2": 4.2,
    "confidence": 84.4,
    "prediction": "1",
    "prode": "1",
    "eloAdvantage": 2.811
  },
  {
    "home": "England",
    "away": "Qatar",
    "homeELO": 1938.1,
    "awayELO": 1589.8,
    "expectedGoals": "2.63 - 0.39",
    "probability_1": 84.2,
    "probability_X": 12.6,
    "probability_2": 3.2,
    "confidence": 84.2,
    "prediction": "1",
    "prode": "1",
    "eloAdvantage": 3.483
  },
  {
    "home": "Algeria",
    "away": "Curaçao",
    "homeELO": 1862.6,
    "awayELO": 1597.2,
    "expectedGoals": "2.47 - 0.49",
    "probability_1": 84.1,
    "probability_X": 11.7,
    "probability_2": 4.2,
    "confidence": 84.1,
    "prediction": "1",
    "prode": "1",
    "eloAdvantage": 2.654
  },
  {
    "home": "Switzerland",
    "away": "Curaçao",
    "homeELO": 1783.1,
    "awayELO": 1597.2,
    "expectedGoals": "2.82 - 0.44",
    "probability_1": 84.1,
    "probability_X": 10.6,
    "probability_2": 5.3,
    "confidence": 84.1,
    "prediction": "1",
    "prode": "1",
    "eloAdvantage": 1.86
  },
  {
    "home": "Croatia",
    "away": "Curaçao",
    "homeELO": 1831.5,
    "awayELO": 1597.2,
    "expectedGoals": "2.75 - 0.41",
    "probability_1": 84.0,
    "probability_X": 10.6,
    "probability_2": 5.3,
    "confidence": 84.0,
    "prediction": "1",
    "prode": "1",
    "eloAdvantage": 2.343
  },
  {
    "home": "Spain",
    "away": "Panama",
    "homeELO": 2031.1,
    "awayELO": 1792.5,
    "expectedGoals": "2.83 - 0.45",
    "probability_1": 83.9,
    "probability_X": 11.8,
    "probability_2": 4.4,
    "confidence": 83.9,
    "prediction": "1",
    "prode": "1",
    "eloAdvantage": 2.386
  },
  {
    "home": "Argentina",
    "away": "Cabo Verde",
    "homeELO": 1991.6,
    "awayELO": 1614.3,
    "expectedGoals": "2.13 - 0.29",
    "probability_1": 83.8,
    "probability_X": 13.2,
    "probability_2": 3.1,
    "confidence": 83.8,
    "prediction": "1",
    "prode": "1",
    "eloAdvantage": 3.773
  },
  {
    "home": "Spain",
    "away": "South Africa",
    "homeELO": 2031.1,
    "awayELO": 1647.3,
    "expectedGoals": "2.35 - 0.41",
    "probability_1": 83.2,
    "probability_X": 13.5,
    "probability_2": 3.3,
    "confidence": 83.2,
    "prediction": "1",
    "prode": "1",
    "eloAdvantage": 3.838
  },
  {
    "home": "Australia",
    "away": "Curaçao",
    "homeELO": 1891.1,
    "awayELO": 1597.2,
    "expectedGoals": "2.16 - 0.42",
    "probability_1": 83.2,
    "probability_X": 12.8,
    "probability_2": 4.0,
    "confidence": 83.2,
    "prediction": "1",
    "prode": "1",
    "eloAdvantage": 2.94
  },
  {
    "home": "Germany",
    "away": "Qatar",
    "homeELO": 1878.7,
    "awayELO": 1589.8,
    "expectedGoals": "3.08 - 0.63",
    "probability_1": 83.0,
    "probability_X": 11.5,
    "probability_2": 5.5,
    "confidence": 83.0,
    "prediction": "1",
    "prode": "1",
    "eloAdvantage": 2.889
  },
  {
    "home": "Brazil",
    "away": "Haiti",
    "homeELO": 1906.3,
    "awayELO": 1673.3,
    "expectedGoals": "3.11 - 0.44",
    "probability_1": 82.9,
    "probability_X": 11.4,
    "probability_2": 5.7,
    "confidence": 82.9,
    "prediction": "1",
    "prode": "1",
    "eloAdvantage": 2.33
  },
  {
    "home": "Mexico",
    "away": "Curaçao",
    "homeELO": 1901.6,
    "awayELO": 1597.2,
    "expectedGoals": "2.14 - 0.43",
    "probability_1": 82.9,
    "probability_X": 13.0,
    "probability_2": 4.2,
    "confidence": 82.9,
    "prediction": "1",
    "prode": "1",
    "eloAdvantage": 3.044
  },
  {
    "home": "Argentina",
    "away": "Ghana",
    "homeELO": 1991.6,
    "awayELO": 1587.4,
    "expectedGoals": "2.02 - 0.33",
    "probability_1": 82.7,
    "probability_X": 14.0,
    "probability_2": 3.3,
    "confidence": 82.7,
    "prediction": "1",
    "prode": "1",
    "eloAdvantage": 4.043
  },
  {
    "home": "France",
    "away": "Haiti",
    "homeELO": 1964.8,
    "awayELO": 1673.3,
    "expectedGoals": "2.96 - 0.46",
    "probability_1": 82.5,
    "probability_X": 12.3,
    "probability_2": 5.2,
    "confidence": 82.5,
    "prediction": "1",
    "prode": "1",
    "eloAdvantage": 2.914
  },
  {
    "home": "Senegal",
    "away": "Curaçao",
    "homeELO": 1867.3,
    "awayELO": 1597.2,
    "expectedGoals": "2.26 - 0.41",
    "probability_1": 82.5,
    "probability_X": 12.8,
    "probability_2": 4.7,
    "confidence": 82.5,
    "prediction": "1",
    "prode": "1",
    "eloAdvantage": 2.701
  },
  {
    "home": "Spain",
    "away": "Saudi Arabia",
    "homeELO": 2031.1,
    "awayELO": 1680.4,
    "expectedGoals": "2.23 - 0.38",
    "probability_1": 82.1,
    "probability_X": 14.1,
    "probability_2": 3.8,
    "confidence": 82.1,
    "prediction": "1",
    "prode": "1",
    "eloAdvantage": 3.507
  },
  {
    "home": "Spain",
    "away": "Tunisia",
    "homeELO": 2031.1,
    "awayELO": 1632.0,
    "expectedGoals": "2.03 - 0.46",
    "probability_1": 82.0,
    "probability_X": 14.2,
    "probability_2": 3.8,
    "confidence": 82.0,
    "prediction": "1",
    "prode": "1",
    "eloAdvantage": 3.991
  },
  {
    "home": "Iran",
    "away": "Curaçao",
    "homeELO": 1867.4,
    "awayELO": 1597.2,
    "expectedGoals": "2.24 - 0.48",
    "probability_1": 82.0,
    "probability_X": 13.2,
    "probability_2": 4.8,
    "confidence": 82.0,
    "prediction": "1",
    "prode": "1",
    "eloAdvantage": 2.702
  },
  {
    "home": "Argentina",
    "away": "Bosnia and Herzegovina",
    "homeELO": 1991.6,
    "awayELO": 1550.2,
    "expectedGoals": "1.98 - 0.34",
    "probability_1": 81.9,
    "probability_X": 14.9,
    "probability_2": 3.2,
    "confidence": 81.9,
    "prediction": "1",
    "prode": "1",
    "eloAdvantage": 4.414
  },
  {
    "home": "England",
    "away": "Haiti",
    "homeELO": 1938.1,
    "awayELO": 1673.3,
    "expectedGoals": "2.78 - 0.36",
    "probability_1": 81.9,
    "probability_X": 13.4,
    "probability_2": 4.6,
    "confidence": 81.9,
    "prediction": "1",
    "prode": "1",
    "eloAdvantage": 2.648
  },
  {
    "home": "Colombia",
    "away": "Qatar",
    "homeELO": 1885.6,
    "awayELO": 1589.8,
    "expectedGoals": "2.57 - 0.52",
    "probability_1": 81.9,
    "probability_X": 13.3,
    "probability_2": 4.8,
    "confidence": 81.9,
    "prediction": "1",
    "prode": "1",
    "eloAdvantage": 2.957
  },
  {
    "home": "Netherlands",
    "away": "Qatar",
    "homeELO": 1866.5,
    "awayELO": 1589.8,
    "expectedGoals": "2.82 - 0.60",
    "probability_1": 81.9,
    "probability_X": 13.1,
    "probability_2": 5.1,
    "confidence": 81.9,
    "prediction": "1",
    "prode": "1",
    "eloAdvantage": 2.766
  },
  {
    "home": "Portugal",
    "away": "Haiti",
    "homeELO": 1902.8,
    "awayELO": 1673.3,
    "expectedGoals": "3.09 - 0.47",
    "probability_1": 81.8,
    "probability_X": 12.3,
    "probability_2": 5.9,
    "confidence": 81.8,
    "prediction": "1",
    "prode": "1",
    "eloAdvantage": 2.294
  },
  {
    "home": "Uruguay",
    "away": "Curaçao",
    "homeELO": 1805.9,
    "awayELO": 1597.2,
    "expectedGoals": "2.26 - 0.32",
    "probability_1": 81.5,
    "probability_X": 13.2,
    "probability_2": 5.3,
    "confidence": 81.5,
    "prediction": "1",
    "prode": "1",
    "eloAdvantage": 2.088
  },
  {
    "home": "Argentina",
    "away": "Panama",
    "homeELO": 1991.6,
    "awayELO": 1792.5,
    "expectedGoals": "2.32 - 0.35",
    "probability_1": 81.4,
    "probability_X": 13.5,
    "probability_2": 5.1,
    "confidence": 81.4,
    "prediction": "1",
    "prode": "1",
    "eloAdvantage": 1.991
  },
  {
    "home": "Argentina",
    "away": "New Zealand",
    "homeELO": 1991.6,
    "awayELO": 1669.9,
    "expectedGoals": "2.00 - 0.26",
    "probability_1": 81.4,
    "probability_X": 14.8,
    "probability_2": 3.7,
    "confidence": 81.4,
    "prediction": "1",
    "prode": "1",
    "eloAdvantage": 3.217
  },
  {
    "home": "France",
    "away": "Cabo Verde",
    "homeELO": 1964.8,
    "awayELO": 1614.3,
    "expectedGoals": "2.18 - 0.42",
    "probability_1": 81.3,
    "probability_X": 14.2,
    "probability_2": 4.6,
    "confidence": 81.3,
    "prediction": "1",
    "prode": "1",
    "eloAdvantage": 3.504
  },
  {
    "home": "Brazil",
    "away": "Cabo Verde",
    "homeELO": 1906.3,
    "awayELO": 1614.3,
    "expectedGoals": "2.29 - 0.40",
    "probability_1": 81.3,
    "probability_X": 13.7,
    "probability_2": 5.0,
    "confidence": 81.3,
    "prediction": "1",
    "prode": "1",
    "eloAdvantage": 2.92
  },
  {
    "home": "Brazil",
    "away": "Ghana",
    "homeELO": 1906.3,
    "awayELO": 1587.4,
    "expectedGoals": "2.17 - 0.46",
    "probability_1": 81.0,
    "probability_X": 14.0,
    "probability_2": 5.0,
    "confidence": 81.0,
    "prediction": "1",
    "prode": "1",
    "eloAdvantage": 3.19
  },
  {
    "home": "England",
    "away": "Cabo Verde",
    "homeELO": 1938.1,
    "awayELO": 1614.3,
    "expectedGoals": "2.05 - 0.33",
    "probability_1": 80.7,
    "probability_X": 15.3,
    "probability_2": 4.0,
    "confidence": 80.7,
    "prediction": "1",
    "prode": "1",
    "eloAdvantage": 3.238
  },
  {
    "home": "Portugal",
    "away": "Ghana",
    "homeELO": 1902.8,
    "awayELO": 1587.4,
    "expectedGoals": "2.16 - 0.50",
    "probability_1": 80.6,
    "probability_X": 14.3,
    "probability_2": 5.1,
    "confidence": 80.6,
    "prediction": "1",
    "prode": "1",
    "eloAdvantage": 3.154
  },
  {
    "home": "Ecuador",
    "away": "Curaçao",
    "homeELO": 1826.0,
    "awayELO": 1597.2,
    "expectedGoals": "1.97 - 0.30",
    "probability_1": 80.4,
    "probability_X": 14.8,
    "probability_2": 4.8,
    "confidence": 80.4,
    "prediction": "1",
    "prode": "1",
    "eloAdvantage": 2.288
  },
  {
    "home": "Germany",
    "away": "Haiti",
    "homeELO": 1878.7,
    "awayELO": 1673.3,
    "expectedGoals": "3.26 - 0.59",
    "probability_1": 80.2,
    "probability_X": 12.0,
    "probability_2": 7.8,
    "confidence": 80.2,
    "prediction": "1",
    "prode": "1",
    "eloAdvantage": 2.054
  },
  {
    "home": "Turkey",
    "away": "Curaçao",
    "homeELO": 1770.6,
    "awayELO": 1597.2,
    "expectedGoals": "2.63 - 0.57",
    "probability_1": 80.2,
    "probability_X": 12.9,
    "probability_2": 6.9,
    "confidence": 80.2,
    "prediction": "1",
    "prode": "1",
    "eloAdvantage": 1.735
  },
  {
    "home": "Portugal",
    "away": "Cabo Verde",
    "homeELO": 1902.8,
    "awayELO": 1614.3,
    "expectedGoals": "2.28 - 0.43",
    "probability_1": 80.1,
    "probability_X": 14.6,
    "probability_2": 5.3,
    "confidence": 80.1,
    "prediction": "1",
    "prode": "1",
    "eloAdvantage": 2.884
  },
  {
    "home": "Spain",
    "away": "Iraq",
    "homeELO": 2031.1,
    "awayELO": 1723.4,
    "expectedGoals": "2.23 - 0.38",
    "probability_1": 79.8,
    "probability_X": 15.9,
    "probability_2": 4.3,
    "confidence": 79.8,
    "prediction": "1",
    "prode": "1",
    "eloAdvantage": 3.077
  },
  {
    "home": "Argentina",
    "away": "Jordan",
    "homeELO": 1991.6,
    "awayELO": 1750.0,
    "expectedGoals": "2.24 - 0.39",
    "probability_1": 79.8,
    "probability_X": 14.5,
    "probability_2": 5.7,
    "confidence": 79.8,
    "prediction": "1",
    "prode": "1",
    "eloAdvantage": 2.416
  },
  {
    "home": "France",
    "away": "Ghana",
    "homeELO": 1964.8,
    "awayELO": 1587.4,
    "expectedGoals": "2.07 - 0.48",
    "probability_1": 79.8,
    "probability_X": 15.1,
    "probability_2": 5.1,
    "confidence": 79.8,
    "prediction": "1",
    "prode": "1",
    "eloAdvantage": 3.774
  },
  {
    "home": "Portugal",
    "away": "Bosnia and Herzegovina",
    "homeELO": 1902.8,
    "awayELO": 1550.2,
    "expectedGoals": "2.11 - 0.50",
    "probability_1": 79.8,
    "probability_X": 15.3,
    "probability_2": 4.9,
    "confidence": 79.8,
    "prediction": "1",
    "prode": "1",
    "eloAdvantage": 3.525
  },
  {
    "home": "Belgium",
    "away": "Qatar",
    "homeELO": 1806.1,
    "awayELO": 1589.8,
    "expectedGoals": "2.64 - 0.57",
    "probability_1": 79.8,
    "probability_X": 13.7,
    "probability_2": 6.4,
    "confidence": 79.8,
    "prediction": "1",
    "prode": "1",
    "eloAdvantage": 2.163
  },
  {
    "home": "Spain",
    "away": "Czech Republic",
    "homeELO": 2031.1,
    "awayELO": 1655.7,
    "expectedGoals": "2.19 - 0.62",
    "probability_1": 79.7,
    "probability_X": 15.0,
    "probability_2": 5.4,
    "confidence": 79.7,
    "prediction": "1",
    "prode": "1",
    "eloAdvantage": 3.754
  },
  {
    "home": "Portugal",
    "away": "New Zealand",
    "homeELO": 1902.8,
    "awayELO": 1669.9,
    "expectedGoals": "2.13 - 0.39",
    "probability_1": 79.6,
    "probability_X": 14.9,
    "probability_2": 5.5,
    "confidence": 79.6,
    "prediction": "1",
    "prode": "1",
    "eloAdvantage": 2.328
  },
  {
    "home": "Germany",
    "away": "Cabo Verde",
    "homeELO": 1878.7,
    "awayELO": 1614.3,
    "expectedGoals": "2.40 - 0.54",
    "probability_1": 79.6,
    "probability_X": 13.8,
    "probability_2": 6.6,
    "confidence": 79.6,
    "prediction": "1",
    "prode": "1",
    "eloAdvantage": 2.644
  },
  {
    "home": "England",
    "away": "Ghana",
    "homeELO": 1938.1,
    "awayELO": 1587.4,
    "expectedGoals": "1.94 - 0.38",
    "probability_1": 79.5,
    "probability_X": 16.2,
    "probability_2": 4.3,
    "confidence": 79.5,
    "prediction": "1",
    "prode": "1",
    "eloAdvantage": 3.508
  },
  {
    "home": "England",
    "away": "Bosnia and Herzegovina",
    "homeELO": 1938.1,
    "awayELO": 1550.2,
    "expectedGoals": "1.90 - 0.38",
    "probability_1": 79.5,
    "probability_X": 16.6,
    "probability_2": 4.0,
    "confidence": 79.5,
    "prediction": "1",
    "prode": "1",
    "eloAdvantage": 3.879
  },
  {
    "home": "Austria",
    "away": "Curaçao",
    "homeELO": 1737.8,
    "awayELO": 1597.2,
    "expectedGoals": "2.45 - 0.44",
    "probability_1": 79.5,
    "probability_X": 13.3,
    "probability_2": 7.2,
    "confidence": 79.5,
    "prediction": "1",
    "prode": "1",
    "eloAdvantage": 1.406
  },
  {
    "home": "Argentina",
    "away": "South Africa",
    "homeELO": 1991.6,
    "awayELO": 1647.3,
    "expectedGoals": "1.93 - 0.32",
    "probability_1": 79.4,
    "probability_X": 16.6,
    "probability_2": 4.0,
    "confidence": 79.4,
    "prediction": "1",
    "prode": "1",
    "eloAdvantage": 3.443
  },
  {
    "home": "Brazil",
    "away": "Bosnia and Herzegovina",
    "homeELO": 1906.3,
    "awayELO": 1550.2,
    "expectedGoals": "2.13 - 0.46",
    "probability_1": 79.4,
    "probability_X": 15.6,
    "probability_2": 5.0,
    "confidence": 79.4,
    "prediction": "1",
    "prode": "1",
    "eloAdvantage": 3.561
  },
  {
    "home": "South Korea",
    "away": "Curaçao",
    "homeELO": 1852.3,
    "awayELO": 1597.2,
    "expectedGoals": "2.16 - 0.53",
    "probability_1": 79.3,
    "probability_X": 14.6,
    "probability_2": 6.1,
    "confidence": 79.3,
    "prediction": "1",
    "prode": "1",
    "eloAdvantage": 2.551
  },
  {
    "home": "England",
    "away": "New Zealand",
    "homeELO": 1938.1,
    "awayELO": 1669.9,
    "expectedGoals": "1.92 - 0.30",
    "probability_1": 79.2,
    "probability_X": 16.4,
    "probability_2": 4.4,
    "confidence": 79.2,
    "prediction": "1",
    "prode": "1",
    "eloAdvantage": 2.682
  },
  {
    "home": "Germany",
    "away": "Ghana",
    "homeELO": 1878.7,
    "awayELO": 1587.4,
    "expectedGoals": "2.27 - 0.62",
    "probability_1": 79.1,
    "probability_X": 14.2,
    "probability_2": 6.7,
    "confidence": 79.1,
    "prediction": "1",
    "prode": "1",
    "eloAdvantage": 2.914
  },
  {
    "home": "France",
    "away": "Bosnia and Herzegovina",
    "homeELO": 1964.8,
    "awayELO": 1550.2,
    "expectedGoals": "2.03 - 0.49",
    "probability_1": 79.0,
    "probability_X": 16.1,
    "probability_2": 4.9,
    "confidence": 79.0,
    "prediction": "1",
    "prode": "1",
    "eloAdvantage": 4.146
  },
  {
    "home": "United States",
    "away": "Curaçao",
    "homeELO": 1807.7,
    "awayELO": 1597.2,
    "expectedGoals": "2.24 - 0.56",
    "probability_1": 79.0,
    "probability_X": 13.7,
    "probability_2": 7.3,
    "confidence": 79.0,
    "prediction": "1",
    "prode": "1",
    "eloAdvantage": 2.105
  },
  {
    "home": "France",
    "away": "New Zealand",
    "homeELO": 1964.8,
    "awayELO": 1669.9,
    "expectedGoals": "2.05 - 0.38",
    "probability_1": 78.8,
    "probability_X": 15.8,
    "probability_2": 5.4,
    "confidence": 78.8,
    "prediction": "1",
    "prode": "1",
    "eloAdvantage": 2.949
  },
  {
    "home": "Brazil",
    "away": "New Zealand",
    "homeELO": 1906.3,
    "awayELO": 1669.9,
    "expectedGoals": "2.15 - 0.36",
    "probability_1": 78.7,
    "probability_X": 15.2,
    "probability_2": 6.1,
    "confidence": 78.7,
    "prediction": "1",
    "prode": "1",
    "eloAdvantage": 2.364
  },
  {
    "home": "Colombia",
    "away": "Haiti",
    "homeELO": 1885.6,
    "awayELO": 1673.3,
    "expectedGoals": "2.72 - 0.48",
    "probability_1": 78.5,
    "probability_X": 14.4,
    "probability_2": 7.0,
    "confidence": 78.5,
    "prediction": "1",
    "prode": "1",
    "eloAdvantage": 2.122
  },
  {
    "home": "Sweden",
    "away": "Curaçao",
    "homeELO": 1701.6,
    "awayELO": 1597.2,
    "expectedGoals": "2.79 - 0.59",
    "probability_1": 78.5,
    "probability_X": 11.8,
    "probability_2": 9.7,
    "confidence": 78.5,
    "prediction": "1",
    "prode": "1",
    "eloAdvantage": 1.045
  },
  {
    "home": "Morocco",
    "away": "Qatar",
    "homeELO": 1950.5,
    "awayELO": 1589.8,
    "expectedGoals": "1.87 - 0.39",
    "probability_1": 78.4,
    "probability_X": 17.1,
    "probability_2": 4.5,
    "confidence": 78.4,
    "prediction": "1",
    "prode": "1",
    "eloAdvantage": 3.607
  },
  {
    "home": "Germany",
    "away": "Bosnia and Herzegovina",
    "homeELO": 1878.7,
    "awayELO": 1550.2,
    "expectedGoals": "2.23 - 0.62",
    "probability_1": 78.4,
    "probability_X": 15.2,
    "probability_2": 6.5,
    "confidence": 78.4,
    "prediction": "1",
    "prode": "1",
    "eloAdvantage": 3.285
  },
  {
    "home": "Netherlands",
    "away": "Haiti",
    "homeELO": 1866.5,
    "awayELO": 1673.3,
    "expectedGoals": "2.98 - 0.56",
    "probability_1": 78.3,
    "probability_X": 14.3,
    "probability_2": 7.5,
    "confidence": 78.3,
    "prediction": "1",
    "prode": "1",
    "eloAdvantage": 1.931
  },
  {
    "home": "England",
    "away": "Panama",
    "homeELO": 1938.1,
    "awayELO": 1792.5,
    "expectedGoals": "2.23 - 0.40",
    "probability_1": 77.9,
    "probability_X": 15.7,
    "probability_2": 6.5,
    "confidence": 77.9,
    "prediction": "1",
    "prode": "1",
    "eloAdvantage": 1.456
  },
  {
    "home": "Scotland",
    "away": "Curaçao",
    "homeELO": 1747.6,
    "awayELO": 1597.2,
    "expectedGoals": "2.14 - 0.51",
    "probability_1": 77.9,
    "probability_X": 15.1,
    "probability_2": 7.1,
    "confidence": 77.9,
    "prediction": "1",
    "prode": "1",
    "eloAdvantage": 1.504
  },
  {
    "home": "Argentina",
    "away": "Iraq",
    "homeELO": 1991.6,
    "awayELO": 1723.4,
    "expectedGoals": "1.82 - 0.30",
    "probability_1": 77.7,
    "probability_X": 17.7,
    "probability_2": 4.6,
    "confidence": 77.7,
    "prediction": "1",
    "prode": "1",
    "eloAdvantage": 2.683
  },
  {
    "home": "Norway",
    "away": "Qatar",
    "homeELO": 1837.3,
    "awayELO": 1589.8,
    "expectedGoals": "2.51 - 0.64",
    "probability_1": 77.7,
    "probability_X": 15.7,
    "probability_2": 6.6,
    "confidence": 77.7,
    "prediction": "1",
    "prode": "1",
    "eloAdvantage": 2.475
  },
  {
    "home": "Argentina",
    "away": "Tunisia",
    "homeELO": 1991.6,
    "awayELO": 1632.0,
    "expectedGoals": "1.66 - 0.36",
    "probability_1": 77.3,
    "probability_X": 18.1,
    "probability_2": 4.5,
    "confidence": 77.3,
    "prediction": "1",
    "prode": "1",
    "eloAdvantage": 3.596
  },
  {
    "home": "France",
    "away": "South Africa",
    "homeELO": 1964.8,
    "awayELO": 1647.3,
    "expectedGoals": "1.97 - 0.46",
    "probability_1": 77.3,
    "probability_X": 17.0,
    "probability_2": 5.7,
    "confidence": 77.3,
    "prediction": "1",
    "prode": "1",
    "eloAdvantage": 3.174
  },
  {
    "home": "Netherlands",
    "away": "Cabo Verde",
    "homeELO": 1866.5,
    "awayELO": 1614.3,
    "expectedGoals": "2.20 - 0.51",
    "probability_1": 77.2,
    "probability_X": 16.2,
    "probability_2": 6.6,
    "confidence": 77.2,
    "prediction": "1",
    "prode": "1",
    "eloAdvantage": 2.521
  },
  {
    "home": "Belgium",
    "away": "Haiti",
    "homeELO": 1806.1,
    "awayELO": 1673.3,
    "expectedGoals": "2.79 - 0.53",
    "probability_1": 77.2,
    "probability_X": 14.0,
    "probability_2": 8.8,
    "confidence": 77.2,
    "prediction": "1",
    "prode": "1",
    "eloAdvantage": 1.327
  },
  {
    "home": "Argentina",
    "away": "Saudi Arabia",
    "homeELO": 1991.6,
    "awayELO": 1680.4,
    "expectedGoals": "1.82 - 0.30",
    "probability_1": 77.0,
    "probability_X": 18.1,
    "probability_2": 4.9,
    "confidence": 77.0,
    "prediction": "1",
    "prode": "1",
    "eloAdvantage": 3.112
  },
  {
    "home": "France",
    "away": "Panama",
    "homeELO": 1964.8,
    "awayELO": 1792.5,
    "expectedGoals": "2.37 - 0.51",
    "probability_1": 77.0,
    "probability_X": 15.1,
    "probability_2": 7.9,
    "confidence": 77.0,
    "prediction": "1",
    "prode": "1",
    "eloAdvantage": 1.723
  },
  {
    "home": "Morocco",
    "away": "Haiti",
    "homeELO": 1950.5,
    "awayELO": 1673.3,
    "expectedGoals": "1.98 - 0.36",
    "probability_1": 77.0,
    "probability_X": 17.4,
    "probability_2": 5.6,
    "confidence": 77.0,
    "prediction": "1",
    "prode": "1",
    "eloAdvantage": 2.772
  },
  {
    "home": "Colombia",
    "away": "Cabo Verde",
    "homeELO": 1885.6,
    "awayELO": 1614.3,
    "expectedGoals": "2.00 - 0.44",
    "probability_1": 77.0,
    "probability_X": 16.8,
    "probability_2": 6.2,
    "confidence": 77.0,
    "prediction": "1",
    "prode": "1",
    "eloAdvantage": 2.712
  },
  {
    "home": "Germany",
    "away": "New Zealand",
    "homeELO": 1878.7,
    "awayELO": 1669.9,
    "expectedGoals": "2.25 - 0.49",
    "probability_1": 77.0,
    "probability_X": 15.2,
    "probability_2": 7.9,
    "confidence": 77.0,
    "prediction": "1",
    "prode": "1",
    "eloAdvantage": 2.088
  },
  {
    "home": "Canada",
    "away": "Curaçao",
    "homeELO": 1794.1,
    "awayELO": 1597.2,
    "expectedGoals": "1.98 - 0.50",
    "probability_1": 76.9,
    "probability_X": 16.3,
    "probability_2": 6.7,
    "confidence": 76.9,
    "prediction": "1",
    "prode": "1",
    "eloAdvantage": 1.97
  },
  {
    "home": "Brazil",
    "away": "Panama",
    "homeELO": 1906.3,
    "awayELO": 1792.5,
    "expectedGoals": "2.49 - 0.48",
    "probability_1": 76.6,
    "probability_X": 14.5,
    "probability_2": 8.9,
    "confidence": 76.6,
    "prediction": "1",
    "prode": "1",
    "eloAdvantage": 1.138
  },
  {
    "home": "Japan",
    "away": "Qatar",
    "homeELO": 1923.1,
    "awayELO": 1589.8,
    "expectedGoals": "2.18 - 0.55",
    "probability_1": 76.5,
    "probability_X": 17.5,
    "probability_2": 6.0,
    "confidence": 76.5,
    "prediction": "1",
    "prode": "1",
    "eloAdvantage": 3.332
  },
  {
    "home": "Brazil",
    "away": "South Africa",
    "homeELO": 1906.3,
    "awayELO": 1647.3,
    "expectedGoals": "2.07 - 0.44",
    "probability_1": 76.5,
    "probability_X": 17.1,
    "probability_2": 6.4,
    "confidence": 76.5,
    "prediction": "1",
    "prode": "1",
    "eloAdvantage": 2.59
  },
  {
    "home": "Portugal",
    "away": "Panama",
    "homeELO": 1902.8,
    "awayELO": 1792.5,
    "expectedGoals": "2.47 - 0.52",
    "probability_1": 76.5,
    "probability_X": 14.9,
    "probability_2": 8.6,
    "confidence": 76.5,
    "prediction": "1",
    "prode": "1",
    "eloAdvantage": 1.103
  },
  {
    "home": "Ivory Coast",
    "away": "Curaçao",
    "homeELO": 1830.5,
    "awayELO": 1597.2,
    "expectedGoals": "1.85 - 0.43",
    "probability_1": 76.4,
    "probability_X": 17.0,
    "probability_2": 6.7,
    "confidence": 76.4,
    "prediction": "1",
    "prode": "1",
    "eloAdvantage": 2.333
  },
  {
    "home": "Spain",
    "away": "Sweden",
    "homeELO": 2031.1,
    "awayELO": 1701.6,
    "expectedGoals": "2.20 - 0.77",
    "probability_1": 76.3,
    "probability_X": 16.3,
    "probability_2": 7.4,
    "confidence": 76.3,
    "prediction": "1",
    "prode": "1",
    "eloAdvantage": 3.295
  },
  {
    "home": "France",
    "away": "Jordan",
    "homeELO": 1964.8,
    "awayELO": 1750.0,
    "expectedGoals": "2.29 - 0.56",
    "probability_1": 76.2,
    "probability_X": 15.6,
    "probability_2": 8.2,
    "confidence": 76.2,
    "prediction": "1",
    "prode": "1",
    "eloAdvantage": 2.147
  },
  {
    "home": "England",
    "away": "Jordan",
    "homeELO": 1938.1,
    "awayELO": 1750.0,
    "expectedGoals": "2.15 - 0.44",
    "probability_1": 76.1,
    "probability_X": 16.7,
    "probability_2": 7.2,
    "confidence": 76.1,
    "prediction": "1",
    "prode": "1",
    "eloAdvantage": 1.881
  },
  {
    "home": "Portugal",
    "away": "South Africa",
    "homeELO": 1902.8,
    "awayELO": 1647.3,
    "expectedGoals": "2.06 - 0.47",
    "probability_1": 76.1,
    "probability_X": 17.4,
    "probability_2": 6.4,
    "confidence": 76.1,
    "prediction": "1",
    "prode": "1",
    "eloAdvantage": 2.554
  },
  {
    "home": "Brazil",
    "away": "Saudi Arabia",
    "homeELO": 1906.3,
    "awayELO": 1680.4,
    "expectedGoals": "1.96 - 0.41",
    "probability_1": 76.0,
    "probability_X": 17.1,
    "probability_2": 6.9,
    "confidence": 76.0,
    "prediction": "1",
    "prode": "1",
    "eloAdvantage": 2.259
  },
  {
    "home": "England",
    "away": "South Africa",
    "homeELO": 1938.1,
    "awayELO": 1647.3,
    "expectedGoals": "1.85 - 0.36",
    "probability_1": 75.9,
    "probability_X": 19.0,
    "probability_2": 5.1,
    "confidence": 75.9,
    "prediction": "1",
    "prode": "1",
    "eloAdvantage": 2.908
  },
  {
    "home": "Brazil",
    "away": "Jordan",
    "homeELO": 1906.3,
    "awayELO": 1750.0,
    "expectedGoals": "2.41 - 0.53",
    "probability_1": 75.9,
    "probability_X": 14.9,
    "probability_2": 9.2,
    "confidence": 75.9,
    "prediction": "1",
    "prode": "1",
    "eloAdvantage": 1.563
  },
  {
    "home": "Belgium",
    "away": "Cabo Verde",
    "homeELO": 1806.1,
    "awayELO": 1614.3,
    "expectedGoals": "2.05 - 0.49",
    "probability_1": 75.8,
    "probability_X": 16.5,
    "probability_2": 7.6,
    "confidence": 75.8,
    "prediction": "1",
    "prode": "1",
    "eloAdvantage": 1.917
  },
  {
    "home": "Portugal",
    "away": "Jordan",
    "homeELO": 1902.8,
    "awayELO": 1750.0,
    "expectedGoals": "2.39 - 0.57",
    "probability_1": 75.7,
    "probability_X": 15.3,
    "probability_2": 9.0,
    "confidence": 75.7,
    "prediction": "1",
    "prode": "1",
    "eloAdvantage": 1.527
  },
  {
    "home": "Portugal",
    "away": "Saudi Arabia",
    "homeELO": 1902.8,
    "awayELO": 1680.4,
    "expectedGoals": "1.95 - 0.44",
    "probability_1": 75.7,
    "probability_X": 17.4,
    "probability_2": 6.9,
    "confidence": 75.7,
    "prediction": "1",
    "prode": "1",
    "eloAdvantage": 2.223
  },
  {
    "home": "Netherlands",
    "away": "Ghana",
    "homeELO": 1866.5,
    "awayELO": 1587.4,
    "expectedGoals": "2.08 - 0.58",
    "probability_1": 75.6,
    "probability_X": 17.2,
    "probability_2": 7.2,
    "confidence": 75.6,
    "prediction": "1",
    "prode": "1",
    "eloAdvantage": 2.791
  },
  {
    "home": "Argentina",
    "away": "Czech Republic",
    "homeELO": 1991.6,
    "awayELO": 1655.7,
    "expectedGoals": "1.79 - 0.48",
    "probability_1": 75.5,
    "probability_X": 18.3,
    "probability_2": 6.2,
    "confidence": 75.5,
    "prediction": "1",
    "prode": "1",
    "eloAdvantage": 3.359
  },
  {
    "home": "Colombia",
    "away": "Ghana",
    "homeELO": 1885.6,
    "awayELO": 1587.4,
    "expectedGoals": "1.90 - 0.51",
    "probability_1": 75.4,
    "probability_X": 17.8,
    "probability_2": 6.8,
    "confidence": 75.4,
    "prediction": "1",
    "prode": "1",
    "eloAdvantage": 2.982
  },
  {
    "home": "Norway",
    "away": "Haiti",
    "homeELO": 1837.3,
    "awayELO": 1673.3,
    "expectedGoals": "2.65 - 0.59",
    "probability_1": 75.4,
    "probability_X": 16.0,
    "probability_2": 8.6,
    "confidence": 75.4,
    "prediction": "1",
    "prode": "1",
    "eloAdvantage": 1.64
  },
  {
    "home": "Colombia",
    "away": "New Zealand",
    "homeELO": 1885.6,
    "awayELO": 1669.9,
    "expectedGoals": "1.88 - 0.40",
    "probability_1": 75.3,
    "probability_X": 17.8,
    "probability_2": 6.8,
    "confidence": 75.3,
    "prediction": "1",
    "prode": "1",
    "eloAdvantage": 2.157
  },
  {
    "home": "France",
    "away": "Saudi Arabia",
    "homeELO": 1964.8,
    "awayELO": 1680.4,
    "expectedGoals": "1.86 - 0.43",
    "probability_1": 74.8,
    "probability_X": 18.4,
    "probability_2": 6.8,
    "confidence": 74.8,
    "prediction": "1",
    "prode": "1",
    "eloAdvantage": 2.844
  },
  {
    "home": "Netherlands",
    "away": "Bosnia and Herzegovina",
    "homeELO": 1866.5,
    "awayELO": 1550.2,
    "expectedGoals": "2.04 - 0.59",
    "probability_1": 74.7,
    "probability_X": 18.3,
    "probability_2": 6.9,
    "confidence": 74.7,
    "prediction": "1",
    "prode": "1",
    "eloAdvantage": 3.162
  },
  {
    "home": "Spain",
    "away": "United States",
    "homeELO": 2031.1,
    "awayELO": 1807.7,
    "expectedGoals": "2.10 - 0.62",
    "probability_1": 74.6,
    "probability_X": 17.5,
    "probability_2": 7.9,
    "confidence": 74.6,
    "prediction": "1",
    "prode": "1",
    "eloAdvantage": 2.235
  },
  {
    "home": "England",
    "away": "Tunisia",
    "homeELO": 1938.1,
    "awayELO": 1632.0,
    "expectedGoals": "1.60 - 0.41",
    "probability_1": 74.6,
    "probability_X": 19.8,
    "probability_2": 5.6,
    "confidence": 74.6,
    "prediction": "1",
    "prode": "1",
    "eloAdvantage": 3.061
  },
  {
    "home": "Japan",
    "away": "Haiti",
    "homeELO": 1923.1,
    "awayELO": 1673.3,
    "expectedGoals": "2.31 - 0.51",
    "probability_1": 74.6,
    "probability_X": 18.0,
    "probability_2": 7.4,
    "confidence": 74.6,
    "prediction": "1",
    "prode": "1",
    "eloAdvantage": 2.497
  },
  {
    "home": "Colombia",
    "away": "Bosnia and Herzegovina",
    "homeELO": 1885.6,
    "awayELO": 1550.2,
    "expectedGoals": "1.86 - 0.51",
    "probability_1": 74.5,
    "probability_X": 18.9,
    "probability_2": 6.6,
    "confidence": 74.5,
    "prediction": "1",
    "prode": "1",
    "eloAdvantage": 3.353
  },
  {
    "home": "Netherlands",
    "away": "New Zealand",
    "homeELO": 1866.5,
    "awayELO": 1669.9,
    "expectedGoals": "2.06 - 0.46",
    "probability_1": 74.5,
    "probability_X": 17.8,
    "probability_2": 7.7,
    "confidence": 74.5,
    "prediction": "1",
    "prode": "1",
    "eloAdvantage": 1.966
  },
  {
    "home": "England",
    "away": "Saudi Arabia",
    "homeELO": 1938.1,
    "awayELO": 1680.4,
    "expectedGoals": "1.75 - 0.34",
    "probability_1": 74.4,
    "probability_X": 19.8,
    "probability_2": 5.8,
    "confidence": 74.4,
    "prediction": "1",
    "prode": "1",
    "eloAdvantage": 2.577
  },
  {
    "home": "Brazil",
    "away": "Tunisia",
    "homeELO": 1906.3,
    "awayELO": 1632.0,
    "expectedGoals": "1.79 - 0.50",
    "probability_1": 74.4,
    "probability_X": 18.5,
    "probability_2": 7.0,
    "confidence": 74.4,
    "prediction": "1",
    "prode": "1",
    "eloAdvantage": 2.743
  },
  {
    "home": "Germany",
    "away": "South Africa",
    "homeELO": 1878.7,
    "awayELO": 1647.3,
    "expectedGoals": "2.17 - 0.59",
    "probability_1": 74.4,
    "probability_X": 17.1,
    "probability_2": 8.5,
    "confidence": 74.4,
    "prediction": "1",
    "prode": "1",
    "eloAdvantage": 2.314
  },
  {
    "home": "Belgium",
    "away": "Bosnia and Herzegovina",
    "homeELO": 1806.1,
    "awayELO": 1550.2,
    "expectedGoals": "1.91 - 0.57",
    "probability_1": 74.4,
    "probability_X": 18.0,
    "probability_2": 7.6,
    "confidence": 74.4,
    "prediction": "1",
    "prode": "1",
    "eloAdvantage": 2.558
  },
  {
    "home": "Germany",
    "away": "Panama",
    "homeELO": 1878.7,
    "awayELO": 1792.5,
    "expectedGoals": "2.61 - 0.65",
    "probability_1": 74.3,
    "probability_X": 14.4,
    "probability_2": 11.3,
    "confidence": 74.3,
    "prediction": "1",
    "prode": "1",
    "eloAdvantage": 0.862
  },
  {
    "home": "Belgium",
    "away": "Ghana",
    "homeELO": 1806.1,
    "awayELO": 1587.4,
    "expectedGoals": "1.95 - 0.56",
    "probability_1": 74.2,
    "probability_X": 17.6,
    "probability_2": 8.3,
    "confidence": 74.2,
    "prediction": "1",
    "prode": "1",
    "eloAdvantage": 2.187
  },
  {
    "home": "Spain",
    "away": "Paraguay",
    "homeELO": 2031.1,
    "awayELO": 1700.9,
    "expectedGoals": "1.72 - 0.50",
    "probability_1": 74.0,
    "probability_X": 19.6,
    "probability_2": 6.4,
    "confidence": 74.0,
    "prediction": "1",
    "prode": "1",
    "eloAdvantage": 3.302
  },
  {
    "home": "Croatia",
    "away": "Qatar",
    "homeELO": 1831.5,
    "awayELO": 1589.8,
    "expectedGoals": "2.22 - 0.58",
    "probability_1": 74.0,
    "probability_X": 17.5,
    "probability_2": 8.4,
    "confidence": 74.0,
    "prediction": "1",
    "prode": "1",
    "eloAdvantage": 2.416
  },
  {
    "home": "Spain",
    "away": "DR Congo",
    "homeELO": 2031.1,
    "awayELO": 1742.3,
    "expectedGoals": "1.77 - 0.41",
    "probability_1": 73.8,
    "probability_X": 20.3,
    "probability_2": 5.9,
    "confidence": 73.8,
    "prediction": "1",
    "prode": "1",
    "eloAdvantage": 2.888
  },
  {
    "home": "Germany",
    "away": "Saudi Arabia",
    "homeELO": 1878.7,
    "awayELO": 1680.4,
    "expectedGoals": "2.05 - 0.55",
    "probability_1": 73.8,
    "probability_X": 17.1,
    "probability_2": 9.1,
    "confidence": 73.8,
    "prediction": "1",
    "prode": "1",
    "eloAdvantage": 1.983
  },
  {
    "home": "Morocco",
    "away": "Cabo Verde",
    "homeELO": 1950.5,
    "awayELO": 1614.3,
    "expectedGoals": "1.46 - 0.33",
    "probability_1": 73.7,
    "probability_X": 21.0,
    "probability_2": 5.3,
    "confidence": 73.7,
    "prediction": "1",
    "prode": "1",
    "eloAdvantage": 3.362
  },
  {
    "home": "Egypt",
    "away": "Curaçao",
    "homeELO": 1788.5,
    "awayELO": 1597.2,
    "expectedGoals": "1.72 - 0.44",
    "probability_1": 73.7,
    "probability_X": 19.1,
    "probability_2": 7.2,
    "confidence": 73.7,
    "prediction": "1",
    "prode": "1",
    "eloAdvantage": 1.913
  },
  {
    "home": "Spain",
    "away": "Turkey",
    "homeELO": 2031.1,
    "awayELO": 1770.6,
    "expectedGoals": "2.13 - 0.73",
    "probability_1": 73.6,
    "probability_X": 18.6,
    "probability_2": 7.8,
    "confidence": 73.6,
    "prediction": "1",
    "prode": "1",
    "eloAdvantage": 2.605
  },
  {
    "home": "France",
    "away": "Iraq",
    "homeELO": 1964.8,
    "awayELO": 1723.4,
    "expectedGoals": "1.87 - 0.43",
    "probability_1": 73.4,
    "probability_X": 19.4,
    "probability_2": 7.2,
    "confidence": 73.4,
    "prediction": "1",
    "prode": "1",
    "eloAdvantage": 2.414
  },
  {
    "home": "Brazil",
    "away": "Iraq",
    "homeELO": 1906.3,
    "awayELO": 1723.4,
    "expectedGoals": "1.96 - 0.41",
    "probability_1": 73.4,
    "probability_X": 18.7,
    "probability_2": 7.9,
    "confidence": 73.4,
    "prediction": "1",
    "prode": "1",
    "eloAdvantage": 1.829
  },
  {
    "home": "Norway",
    "away": "Cabo Verde",
    "homeELO": 1837.3,
    "awayELO": 1614.3,
    "expectedGoals": "1.95 - 0.54",
    "probability_1": 73.4,
    "probability_X": 18.6,
    "probability_2": 8.0,
    "confidence": 73.4,
    "prediction": "1",
    "prode": "1",
    "eloAdvantage": 2.23
  },
  {
    "home": "Colombia",
    "away": "Panama",
    "homeELO": 1885.6,
    "awayELO": 1792.5,
    "expectedGoals": "2.18 - 0.53",
    "probability_1": 73.3,
    "probability_X": 16.9,
    "probability_2": 9.8,
    "confidence": 73.3,
    "prediction": "1",
    "prode": "1",
    "eloAdvantage": 0.931
  },
  {
    "home": "Germany",
    "away": "Jordan",
    "homeELO": 1878.7,
    "awayELO": 1750.0,
    "expectedGoals": "2.52 - 0.71",
    "probability_1": 73.3,
    "probability_X": 14.9,
    "probability_2": 11.7,
    "confidence": 73.3,
    "prediction": "1",
    "prode": "1",
    "eloAdvantage": 1.287
  },
  {
    "home": "Portugal",
    "away": "Iraq",
    "homeELO": 1902.8,
    "awayELO": 1723.4,
    "expectedGoals": "1.95 - 0.44",
    "probability_1": 73.2,
    "probability_X": 19.1,
    "probability_2": 7.7,
    "confidence": 73.2,
    "prediction": "1",
    "prode": "1",
    "eloAdvantage": 1.794
  },
  {
    "home": "Belgium",
    "away": "New Zealand",
    "homeELO": 1806.1,
    "awayELO": 1669.9,
    "expectedGoals": "1.93 - 0.44",
    "probability_1": 73.0,
    "probability_X": 18.0,
    "probability_2": 9.0,
    "confidence": 73.0,
    "prediction": "1",
    "prode": "1",
    "eloAdvantage": 1.362
  },
  {
    "home": "France",
    "away": "Tunisia",
    "homeELO": 1964.8,
    "awayELO": 1632.0,
    "expectedGoals": "1.70 - 0.52",
    "probability_1": 72.9,
    "probability_X": 19.8,
    "probability_2": 7.3,
    "confidence": 72.9,
    "prediction": "1",
    "prode": "1",
    "eloAdvantage": 3.328
  },
  {
    "home": "England",
    "away": "Iraq",
    "homeELO": 1938.1,
    "awayELO": 1723.4,
    "expectedGoals": "1.75 - 0.34",
    "probability_1": 72.9,
    "probability_X": 20.9,
    "probability_2": 6.2,
    "confidence": 72.9,
    "prediction": "1",
    "prode": "1",
    "eloAdvantage": 2.148
  },
  {
    "home": "Japan",
    "away": "Cabo Verde",
    "homeELO": 1923.1,
    "awayELO": 1614.3,
    "expectedGoals": "1.70 - 0.47",
    "probability_1": 72.9,
    "probability_X": 20.2,
    "probability_2": 6.9,
    "confidence": 72.9,
    "prediction": "1",
    "prode": "1",
    "eloAdvantage": 3.087
  },
  {
    "home": "Portugal",
    "away": "Tunisia",
    "homeELO": 1902.8,
    "awayELO": 1632.0,
    "expectedGoals": "1.78 - 0.54",
    "probability_1": 72.9,
    "probability_X": 19.5,
    "probability_2": 7.6,
    "confidence": 72.9,
    "prediction": "1",
    "prode": "1",
    "eloAdvantage": 2.707
  },
  {
    "home": "Algeria",
    "away": "Qatar",
    "homeELO": 1862.6,
    "awayELO": 1589.8,
    "expectedGoals": "2.00 - 0.70",
    "probability_1": 72.9,
    "probability_X": 18.8,
    "probability_2": 8.2,
    "confidence": 72.9,
    "prediction": "1",
    "prode": "1",
    "eloAdvantage": 2.727
  },
  {
    "home": "Switzerland",
    "away": "Qatar",
    "homeELO": 1783.1,
    "awayELO": 1589.8,
    "expectedGoals": "2.29 - 0.62",
    "probability_1": 72.8,
    "probability_X": 18.2,
    "probability_2": 9.0,
    "confidence": 72.8,
    "prediction": "1",
    "prode": "1",
    "eloAdvantage": 1.933
  },
  {
    "home": "Argentina",
    "away": "Sweden",
    "homeELO": 1991.6,
    "awayELO": 1701.6,
    "expectedGoals": "1.80 - 0.61",
    "probability_1": 72.7,
    "probability_X": 19.2,
    "probability_2": 8.2,
    "confidence": 72.7,
    "prediction": "1",
    "prode": "1",
    "eloAdvantage": 2.9
  },
  {
    "home": "Spain",
    "away": "Uzbekistan",
    "homeELO": 2031.1,
    "awayELO": 1801.4,
    "expectedGoals": "1.83 - 0.44",
    "probability_1": 72.6,
    "probability_X": 20.2,
    "probability_2": 7.3,
    "confidence": 72.6,
    "prediction": "1",
    "prode": "1",
    "eloAdvantage": 2.298
  },
  {
    "home": "Brazil",
    "away": "Czech Republic",
    "homeELO": 1906.3,
    "awayELO": 1655.7,
    "expectedGoals": "1.93 - 0.67",
    "probability_1": 72.5,
    "probability_X": 18.2,
    "probability_2": 9.3,
    "confidence": 72.5,
    "prediction": "1",
    "prode": "1",
    "eloAdvantage": 2.506
  },
  {
    "home": "Czech Republic",
    "away": "Curaçao",
    "homeELO": 1655.7,
    "awayELO": 1597.2,
    "expectedGoals": "2.23 - 0.59",
    "probability_1": 72.4,
    "probability_X": 15.6,
    "probability_2": 11.9,
    "confidence": 72.4,
    "prediction": "1",
    "prode": "1",
    "eloAdvantage": 0.586
  },
  {
    "home": "Morocco",
    "away": "Ghana",
    "homeELO": 1950.5,
    "awayELO": 1587.4,
    "expectedGoals": "1.38 - 0.38",
    "probability_1": 72.3,
    "probability_X": 21.7,
    "probability_2": 6.0,
    "confidence": 72.3,
    "prediction": "1",
    "prode": "1",
    "eloAdvantage": 3.632
  },
  {
    "home": "Colombia",
    "away": "Jordan",
    "homeELO": 1885.6,
    "awayELO": 1750.0,
    "expectedGoals": "2.10 - 0.59",
    "probability_1": 72.3,
    "probability_X": 17.4,
    "probability_2": 10.3,
    "confidence": 72.3,
    "prediction": "1",
    "prode": "1",
    "eloAdvantage": 1.355
  },
  {
    "home": "Senegal",
    "away": "Qatar",
    "homeELO": 1867.3,
    "awayELO": 1589.8,
    "expectedGoals": "1.83 - 0.58",
    "probability_1": 72.2,
    "probability_X": 19.8,
    "probability_2": 8.1,
    "confidence": 72.2,
    "prediction": "1",
    "prode": "1",
    "eloAdvantage": 2.774
  },
  {
    "home": "Spain",
    "away": "Scotland",
    "homeELO": 2031.1,
    "awayELO": 1747.6,
    "expectedGoals": "1.90 - 0.59",
    "probability_1": 72.1,
    "probability_X": 20.2,
    "probability_2": 7.7,
    "confidence": 72.1,
    "prediction": "1",
    "prode": "1",
    "eloAdvantage": 2.835
  },
  {
    "home": "Netherlands",
    "away": "Panama",
    "homeELO": 1866.5,
    "awayELO": 1792.5,
    "expectedGoals": "2.39 - 0.61",
    "probability_1": 72.1,
    "probability_X": 17.0,
    "probability_2": 11.0,
    "confidence": 72.1,
    "prediction": "1",
    "prode": "1",
    "eloAdvantage": 0.74
  },
  {
    "home": "Germany",
    "away": "Tunisia",
    "homeELO": 1878.7,
    "awayELO": 1632.0,
    "expectedGoals": "1.87 - 0.67",
    "probability_1": 71.8,
    "probability_X": 18.6,
    "probability_2": 9.6,
    "confidence": 71.8,
    "prediction": "1",
    "prode": "1",
    "eloAdvantage": 2.467
  },
  {
    "home": "Spain",
    "away": "South Korea",
    "homeELO": 2031.1,
    "awayELO": 1852.3,
    "expectedGoals": "1.97 - 0.60",
    "probability_1": 71.7,
    "probability_X": 19.7,
    "probability_2": 8.6,
    "confidence": 71.7,
    "prediction": "1",
    "prode": "1",
    "eloAdvantage": 1.788
  },
  {
    "home": "England",
    "away": "Czech Republic",
    "homeELO": 1938.1,
    "awayELO": 1655.7,
    "expectedGoals": "1.73 - 0.55",
    "probability_1": 71.7,
    "probability_X": 20.4,
    "probability_2": 7.9,
    "confidence": 71.7,
    "prediction": "1",
    "prode": "1",
    "eloAdvantage": 2.824
  },
  {
    "home": "Portugal",
    "away": "Czech Republic",
    "homeELO": 1902.8,
    "awayELO": 1655.7,
    "expectedGoals": "1.92 - 0.72",
    "probability_1": 71.7,
    "probability_X": 18.6,
    "probability_2": 9.7,
    "confidence": 71.7,
    "prediction": "1",
    "prode": "1",
    "eloAdvantage": 2.47
  },
  {
    "home": "Netherlands",
    "away": "South Africa",
    "homeELO": 1866.5,
    "awayELO": 1647.3,
    "expectedGoals": "1.99 - 0.56",
    "probability_1": 71.7,
    "probability_X": 19.9,
    "probability_2": 8.4,
    "confidence": 71.7,
    "prediction": "1",
    "prode": "1",
    "eloAdvantage": 2.191
  },
  {
    "home": "Belgium",
    "away": "Panama",
    "homeELO": 1806.1,
    "awayELO": 1792.5,
    "expectedGoals": "2.23 - 0.59",
    "probability_1": 71.7,
    "probability_X": 16.4,
    "probability_2": 12.0,
    "confidence": 71.7,
    "prediction": "1",
    "prode": "1",
    "eloAdvantage": 0.136
  },
  {
    "home": "Croatia",
    "away": "Haiti",
    "homeELO": 1831.5,
    "awayELO": 1673.3,
    "expectedGoals": "2.35 - 0.54",
    "probability_1": 71.6,
    "probability_X": 17.4,
    "probability_2": 11.0,
    "confidence": 71.6,
    "prediction": "1",
    "prode": "1",
    "eloAdvantage": 1.581
  },
  {
    "home": "Switzerland",
    "away": "Haiti",
    "homeELO": 1783.1,
    "awayELO": 1673.3,
    "expectedGoals": "2.42 - 0.58",
    "probability_1": 71.6,
    "probability_X": 17.4,
    "probability_2": 10.9,
    "confidence": 71.6,
    "prediction": "1",
    "prode": "1",
    "eloAdvantage": 1.098
  },
  {
    "home": "Colombia",
    "away": "South Africa",
    "homeELO": 1885.6,
    "awayELO": 1647.3,
    "expectedGoals": "1.81 - 0.49",
    "probability_1": 71.5,
    "probability_X": 20.5,
    "probability_2": 8.0,
    "confidence": 71.5,
    "prediction": "1",
    "prode": "1",
    "eloAdvantage": 2.382
  },
  {
    "home": "Argentina",
    "away": "United States",
    "homeELO": 1991.6,
    "awayELO": 1807.7,
    "expectedGoals": "1.72 - 0.49",
    "probability_1": 71.4,
    "probability_X": 20.0,
    "probability_2": 8.7,
    "confidence": 71.4,
    "prediction": "1",
    "prode": "1",
    "eloAdvantage": 1.84
  },
  {
    "home": "Norway",
    "away": "Ghana",
    "homeELO": 1837.3,
    "awayELO": 1587.4,
    "expectedGoals": "1.85 - 0.62",
    "probability_1": 71.4,
    "probability_X": 19.6,
    "probability_2": 9.0,
    "confidence": 71.4,
    "prediction": "1",
    "prode": "1",
    "eloAdvantage": 2.5
  },
  {
    "home": "Japan",
    "away": "New Zealand",
    "homeELO": 1923.1,
    "awayELO": 1669.9,
    "expectedGoals": "1.60 - 0.42",
    "probability_1": 71.3,
    "probability_X": 21.4,
    "probability_2": 7.4,
    "confidence": 71.3,
    "prediction": "1",
    "prode": "1",
    "eloAdvantage": 2.532
  },
  {
    "home": "Germany",
    "away": "Iraq",
    "homeELO": 1878.7,
    "awayELO": 1723.4,
    "expectedGoals": "2.05 - 0.55",
    "probability_1": 71.2,
    "probability_X": 18.6,
    "probability_2": 10.2,
    "confidence": 71.2,
    "prediction": "1",
    "prode": "1",
    "eloAdvantage": 1.553
  },
  {
    "home": "Algeria",
    "away": "Haiti",
    "homeELO": 1862.6,
    "awayELO": 1673.3,
    "expectedGoals": "2.11 - 0.65",
    "probability_1": 71.2,
    "probability_X": 19.3,
    "probability_2": 9.4,
    "confidence": 71.2,
    "prediction": "1",
    "prode": "1",
    "eloAdvantage": 1.892
  },
  {
    "home": "Japan",
    "away": "Ghana",
    "homeELO": 1923.1,
    "awayELO": 1587.4,
    "expectedGoals": "1.61 - 0.54",
    "probability_1": 71.1,
    "probability_X": 21.0,
    "probability_2": 7.9,
    "confidence": 71.1,
    "prediction": "1",
    "prode": "1",
    "eloAdvantage": 3.357
  },
  {
    "home": "Colombia",
    "away": "Saudi Arabia",
    "homeELO": 1885.6,
    "awayELO": 1680.4,
    "expectedGoals": "1.71 - 0.46",
    "probability_1": 71.0,
    "probability_X": 20.6,
    "probability_2": 8.5,
    "confidence": 71.0,
    "prediction": "1",
    "prode": "1",
    "eloAdvantage": 2.051
  },
  {
    "home": "Netherlands",
    "away": "Jordan",
    "homeELO": 1866.5,
    "awayELO": 1750.0,
    "expectedGoals": "2.31 - 0.67",
    "probability_1": 71.0,
    "probability_X": 17.5,
    "probability_2": 11.5,
    "confidence": 71.0,
    "prediction": "1",
    "prode": "1",
    "eloAdvantage": 1.164
  },
  {
    "home": "France",
    "away": "Czech Republic",
    "homeELO": 1964.8,
    "awayELO": 1655.7,
    "expectedGoals": "1.84 - 0.70",
    "probability_1": 70.9,
    "probability_X": 19.5,
    "probability_2": 9.7,
    "confidence": 70.9,
    "prediction": "1",
    "prode": "1",
    "eloAdvantage": 3.091
  },
  {
    "home": "Australia",
    "away": "Qatar",
    "homeELO": 1891.1,
    "awayELO": 1589.8,
    "expectedGoals": "1.75 - 0.59",
    "probability_1": 70.8,
    "probability_X": 21.0,
    "probability_2": 8.2,
    "confidence": 70.8,
    "prediction": "1",
    "prode": "1",
    "eloAdvantage": 3.013
  },
  {
    "home": "Uruguay",
    "away": "Qatar",
    "homeELO": 1805.9,
    "awayELO": 1589.8,
    "expectedGoals": "1.83 - 0.46",
    "probability_1": 70.8,
    "probability_X": 20.9,
    "probability_2": 8.3,
    "confidence": 70.8,
    "prediction": "1",
    "prode": "1",
    "eloAdvantage": 2.161
  },
  {
    "home": "Spain",
    "away": "Canada",
    "homeELO": 2031.1,
    "awayELO": 1794.1,
    "expectedGoals": "1.85 - 0.55",
    "probability_1": 70.7,
    "probability_X": 21.1,
    "probability_2": 8.2,
    "confidence": 70.7,
    "prediction": "1",
    "prode": "1",
    "eloAdvantage": 2.37
  },
  {
    "home": "Morocco",
    "away": "New Zealand",
    "homeELO": 1950.5,
    "awayELO": 1669.9,
    "expectedGoals": "1.37 - 0.30",
    "probability_1": 70.7,
    "probability_X": 23.2,
    "probability_2": 6.1,
    "confidence": 70.7,
    "prediction": "1",
    "prode": "1",
    "eloAdvantage": 2.806
  },
  {
    "home": "Morocco",
    "away": "Bosnia and Herzegovina",
    "homeELO": 1950.5,
    "awayELO": 1550.2,
    "expectedGoals": "1.35 - 0.38",
    "probability_1": 70.5,
    "probability_X": 23.3,
    "probability_2": 6.1,
    "confidence": 70.5,
    "prediction": "1",
    "prode": "1",
    "eloAdvantage": 4.003
  },
  {
    "home": "Norway",
    "away": "Bosnia and Herzegovina",
    "homeELO": 1837.3,
    "awayELO": 1550.2,
    "expectedGoals": "1.81 - 0.63",
    "probability_1": 70.5,
    "probability_X": 20.8,
    "probability_2": 8.8,
    "confidence": 70.5,
    "prediction": "1",
    "prode": "1",
    "eloAdvantage": 2.871
  },
  {
    "home": "Uzbekistan",
    "away": "Curaçao",
    "homeELO": 1801.4,
    "awayELO": 1597.2,
    "expectedGoals": "1.58 - 0.49",
    "probability_1": 70.5,
    "probability_X": 20.7,
    "probability_2": 8.8,
    "confidence": 70.5,
    "prediction": "1",
    "prode": "1",
    "eloAdvantage": 2.042
  },
  {
    "home": "Paraguay",
    "away": "Curaçao",
    "homeELO": 1700.9,
    "awayELO": 1597.2,
    "expectedGoals": "1.81 - 0.46",
    "probability_1": 70.5,
    "probability_X": 18.7,
    "probability_2": 10.8,
    "confidence": 70.5,
    "prediction": "1",
    "prode": "1",
    "eloAdvantage": 1.037
  },
  {
    "home": "Belgium",
    "away": "South Africa",
    "homeELO": 1806.1,
    "awayELO": 1647.3,
    "expectedGoals": "1.86 - 0.54",
    "probability_1": 70.2,
    "probability_X": 20.1,
    "probability_2": 9.7,
    "confidence": 70.2,
    "prediction": "1",
    "prode": "1",
    "eloAdvantage": 1.587
  },
  {
    "home": "Mexico",
    "away": "Haiti",
    "homeELO": 1901.6,
    "awayELO": 1673.3,
    "expectedGoals": "1.83 - 0.57",
    "probability_1": 70.1,
    "probability_X": 20.7,
    "probability_2": 9.2,
    "confidence": 70.1,
    "prediction": "1",
    "prode": "1",
    "eloAdvantage": 2.283
  },
  {
    "home": "Iran",
    "away": "Qatar",
    "homeELO": 1867.4,
    "awayELO": 1589.8,
    "expectedGoals": "1.81 - 0.69",
    "probability_1": 70.1,
    "probability_X": 20.6,
    "probability_2": 9.3,
    "confidence": 70.1,
    "prediction": "1",
    "prode": "1",
    "eloAdvantage": 2.776
  },
  {
    "home": "Netherlands",
    "away": "Saudi Arabia",
    "homeELO": 1866.5,
    "awayELO": 1680.4,
    "expectedGoals": "1.88 - 0.52",
    "probability_1": 70.1,
    "probability_X": 20.5,
    "probability_2": 9.5,
    "confidence": 70.1,
    "prediction": "1",
    "prode": "1",
    "eloAdvantage": 1.86
  },
  {
    "home": "Morocco",
    "away": "Panama",
    "homeELO": 1950.5,
    "awayELO": 1792.5,
    "expectedGoals": "1.58 - 0.40",
    "probability_1": 69.8,
    "probability_X": 21.7,
    "probability_2": 8.5,
    "confidence": 69.8,
    "prediction": "1",
    "prode": "1",
    "eloAdvantage": 1.581
  },
  {
    "home": "Morocco",
    "away": "Jordan",
    "homeELO": 1950.5,
    "awayELO": 1750.0,
    "expectedGoals": "1.53 - 0.44",
    "probability_1": 69.7,
    "probability_X": 21.6,
    "probability_2": 8.7,
    "confidence": 69.7,
    "prediction": "1",
    "prode": "1",
    "eloAdvantage": 2.005
  },
  {
    "home": "Belgium",
    "away": "Saudi Arabia",
    "homeELO": 1806.1,
    "awayELO": 1680.4,
    "expectedGoals": "1.76 - 0.50",
    "probability_1": 69.6,
    "probability_X": 20.1,
    "probability_2": 10.3,
    "confidence": 69.6,
    "prediction": "1",
    "prode": "1",
    "eloAdvantage": 1.257
  },
  {
    "home": "Japan",
    "away": "Panama",
    "homeELO": 1923.1,
    "awayELO": 1792.5,
    "expectedGoals": "1.85 - 0.57",
    "probability_1": 69.5,
    "probability_X": 20.3,
    "probability_2": 10.2,
    "confidence": 69.5,
    "prediction": "1",
    "prode": "1",
    "eloAdvantage": 1.306
  },
  {
    "home": "Colombia",
    "away": "Iraq",
    "homeELO": 1885.6,
    "awayELO": 1723.4,
    "expectedGoals": "1.71 - 0.45",
    "probability_1": 69.5,
    "probability_X": 21.5,
    "probability_2": 8.9,
    "confidence": 69.5,
    "prediction": "1",
    "prode": "1",
    "eloAdvantage": 1.622
  },
  {
    "home": "Norway",
    "away": "New Zealand",
    "homeELO": 1837.3,
    "awayELO": 1669.9,
    "expectedGoals": "1.83 - 0.49",
    "probability_1": 69.5,
    "probability_X": 20.9,
    "probability_2": 9.7,
    "confidence": 69.5,
    "prediction": "1",
    "prode": "1",
    "eloAdvantage": 1.674
  },
  {
    "home": "Australia",
    "away": "Haiti",
    "homeELO": 1891.1,
    "awayELO": 1673.3,
    "expectedGoals": "1.85 - 0.55",
    "probability_1": 69.4,
    "probability_X": 21.3,
    "probability_2": 9.3,
    "confidence": 69.4,
    "prediction": "1",
    "prode": "1",
    "eloAdvantage": 2.178
  },
  {
    "home": "Senegal",
    "away": "Haiti",
    "homeELO": 1867.3,
    "awayELO": 1673.3,
    "expectedGoals": "1.94 - 0.54",
    "probability_1": 69.4,
    "probability_X": 20.6,
    "probability_2": 10.0,
    "confidence": 69.4,
    "prediction": "1",
    "prode": "1",
    "eloAdvantage": 1.939
  },
  {
    "home": "Argentina",
    "away": "Turkey",
    "homeELO": 1991.6,
    "awayELO": 1770.6,
    "expectedGoals": "1.74 - 0.57",
    "probability_1": 69.3,
    "probability_X": 21.9,
    "probability_2": 8.8,
    "confidence": 69.3,
    "prediction": "1",
    "prode": "1",
    "eloAdvantage": 2.21
  },
  {
    "home": "Norway",
    "away": "Panama",
    "homeELO": 1837.3,
    "awayELO": 1792.5,
    "expectedGoals": "2.12 - 0.65",
    "probability_1": 69.3,
    "probability_X": 18.6,
    "probability_2": 12.1,
    "confidence": 69.3,
    "prediction": "1",
    "prode": "1",
    "eloAdvantage": 0.448
  }
]