[
  {
    "home": "Argentina",
    "away": "Curaçao",
    "homeELO": 2025.5,
    "awayELO": 1597.2,
    "expectedGoals": "3.73 - 0.22",
    "probability_1": 94.3,
    "probability_X": 4.7,
    "probability_2": 1.1,
    "confidence": 94.3,
    "prediction": "1",
    "prode": "1",
    "eloAdvantage": 4.283
  },
  {
    "home": "Spain",
    "away": "Curaçao",
    "homeELO": 2006.1,
    "awayELO": 1597.2,
    "expectedGoals": "4.16 - 0.33",
    "probability_1": 93.4,
    "probability_X": 5.3,
    "probability_2": 1.2,
    "confidence": 93.4,
    "prediction": "1",
    "prode": "1",
    "eloAdvantage": 4.089
  },
  {
    "home": "France",
    "away": "Curaçao",
    "homeELO": 1997.5,
    "awayELO": 1597.2,
    "expectedGoals": "3.82 - 0.39",
    "probability_1": 92.2,
    "probability_X": 5.9,
    "probability_2": 1.9,
    "confidence": 92.2,
    "prediction": "1",
    "prode": "1",
    "eloAdvantage": 4.003
  },
  {
    "home": "England",
    "away": "Curaçao",
    "homeELO": 1969.7,
    "awayELO": 1597.2,
    "expectedGoals": "3.65 - 0.32",
    "probability_1": 91.8,
    "probability_X": 6.4,
    "probability_2": 1.8,
    "confidence": 91.8,
    "prediction": "1",
    "prode": "1",
    "eloAdvantage": 3.726
  },
  {
    "home": "Germany",
    "away": "Curaçao",
    "homeELO": 1878.7,
    "awayELO": 1597.2,
    "expectedGoals": "4.30 - 0.48",
    "probability_1": 91.2,
    "probability_X": 5.7,
    "probability_2": 3.1,
    "confidence": 91.2,
    "prediction": "1",
    "prode": "1",
    "eloAdvantage": 2.815
  },
  {
    "home": "Brazil",
    "away": "Curaçao",
    "homeELO": 1906.3,
    "awayELO": 1597.2,
    "expectedGoals": "3.86 - 0.41",
    "probability_1": 90.6,
    "probability_X": 6.6,
    "probability_2": 2.8,
    "confidence": 90.6,
    "prediction": "1",
    "prode": "1",
    "eloAdvantage": 3.091
  },
  {
    "home": "Colombia",
    "away": "Curaçao",
    "homeELO": 1919.9,
    "awayELO": 1597.2,
    "expectedGoals": "3.78 - 0.43",
    "probability_1": 90.4,
    "probability_X": 6.9,
    "probability_2": 2.7,
    "confidence": 90.4,
    "prediction": "1",
    "prode": "1",
    "eloAdvantage": 3.227
  },
  {
    "home": "Argentina",
    "away": "Qatar",
    "homeELO": 2025.5,
    "awayELO": 1589.8,
    "expectedGoals": "3.02 - 0.28",
    "probability_1": 89.8,
    "probability_X": 8.5,
    "probability_2": 1.7,
    "confidence": 89.8,
    "prediction": "1",
    "prode": "1",
    "eloAdvantage": 4.356
  },
  {
    "home": "Norway",
    "away": "Curaçao",
    "homeELO": 1873.2,
    "awayELO": 1597.2,
    "expectedGoals": "3.95 - 0.47",
    "probability_1": 89.8,
    "probability_X": 7.2,
    "probability_2": 2.9,
    "confidence": 89.8,
    "prediction": "1",
    "prode": "1",
    "eloAdvantage": 2.76
  },
  {
    "home": "Portugal",
    "away": "Curaçao",
    "homeELO": 1889.8,
    "awayELO": 1597.2,
    "expectedGoals": "3.82 - 0.42",
    "probability_1": 89.6,
    "probability_X": 7.6,
    "probability_2": 2.9,
    "confidence": 89.6,
    "prediction": "1",
    "prode": "1",
    "eloAdvantage": 2.927
  },
  {
    "home": "Netherlands",
    "away": "Curaçao",
    "homeELO": 1866.5,
    "awayELO": 1597.2,
    "expectedGoals": "3.85 - 0.46",
    "probability_1": 88.9,
    "probability_X": 7.7,
    "probability_2": 3.3,
    "confidence": 88.9,
    "prediction": "1",
    "prode": "1",
    "eloAdvantage": 2.693
  },
  {
    "home": "Spain",
    "away": "Qatar",
    "homeELO": 2006.1,
    "awayELO": 1589.8,
    "expectedGoals": "3.37 - 0.42",
    "probability_1": 88.5,
    "probability_X": 9.5,
    "probability_2": 2.0,
    "confidence": 88.5,
    "prediction": "1",
    "prode": "1",
    "eloAdvantage": 4.163
  },
  {
    "home": "Morocco",
    "away": "Curaçao",
    "homeELO": 1950.5,
    "awayELO": 1597.2,
    "expectedGoals": "2.54 - 0.27",
    "probability_1": 88.3,
    "probability_X": 9.4,
    "probability_2": 2.3,
    "confidence": 88.3,
    "prediction": "1",
    "prode": "1",
    "eloAdvantage": 3.534
  },
  {
    "home": "Japan",
    "away": "Curaçao",
    "homeELO": 1923.1,
    "awayELO": 1597.2,
    "expectedGoals": "3.07 - 0.38",
    "probability_1": 88.3,
    "probability_X": 8.9,
    "probability_2": 2.8,
    "confidence": 88.3,
    "prediction": "1",
    "prode": "1",
    "eloAdvantage": 3.259
  },
  {
    "home": "Argentina",
    "away": "Haiti",
    "homeELO": 2025.5,
    "awayELO": 1673.3,
    "expectedGoals": "2.86 - 0.29",
    "probability_1": 86.6,
    "probability_X": 10.5,
    "probability_2": 2.9,
    "confidence": 86.6,
    "prediction": "1",
    "prode": "1",
    "eloAdvantage": 3.521
  },
  {
    "home": "Belgium",
    "away": "Curaçao",
    "homeELO": 1804.6,
    "awayELO": 1597.2,
    "expectedGoals": "3.34 - 0.46",
    "probability_1": 86.6,
    "probability_X": 8.9,
    "probability_2": 4.5,
    "confidence": 86.6,
    "prediction": "1",
    "prode": "1",
    "eloAdvantage": 2.074
  },
  {
    "home": "France",
    "away": "Qatar",
    "homeELO": 1997.5,
    "awayELO": 1589.8,
    "expectedGoals": "3.09 - 0.50",
    "probability_1": 86.3,
    "probability_X": 10.6,
    "probability_2": 3.1,
    "confidence": 86.3,
    "prediction": "1",
    "prode": "1",
    "eloAdvantage": 4.076
  },
  {
    "home": "England",
    "away": "Qatar",
    "homeELO": 1969.7,
    "awayELO": 1589.8,
    "expectedGoals": "2.95 - 0.41",
    "probability_1": 85.9,
    "probability_X": 11.2,
    "probability_2": 2.9,
    "confidence": 85.9,
    "prediction": "1",
    "prode": "1",
    "eloAdvantage": 3.799
  },
  {
    "home": "Brazil",
    "away": "Qatar",
    "homeELO": 1906.3,
    "awayELO": 1589.8,
    "expectedGoals": "3.12 - 0.52",
    "probability_1": 85.2,
    "probability_X": 10.8,
    "probability_2": 4.0,
    "confidence": 85.2,
    "prediction": "1",
    "prode": "1",
    "eloAdvantage": 3.165
  },
  {
    "home": "Spain",
    "away": "Haiti",
    "homeELO": 2006.1,
    "awayELO": 1673.3,
    "expectedGoals": "3.19 - 0.44",
    "probability_1": 85.0,
    "probability_X": 11.7,
    "probability_2": 3.3,
    "confidence": 85.0,
    "prediction": "1",
    "prode": "1",
    "eloAdvantage": 3.328
  },
  {
    "home": "Switzerland",
    "away": "Curaçao",
    "homeELO": 1783.1,
    "awayELO": 1597.2,
    "expectedGoals": "3.11 - 0.46",
    "probability_1": 84.8,
    "probability_X": 10.1,
    "probability_2": 5.2,
    "confidence": 84.8,
    "prediction": "1",
    "prode": "1",
    "eloAdvantage": 1.86
  },
  {
    "home": "Argentina",
    "away": "Panama",
    "homeELO": 2025.5,
    "awayELO": 1746.6,
    "expectedGoals": "2.45 - 0.31",
    "probability_1": 84.7,
    "probability_X": 11.9,
    "probability_2": 3.5,
    "confidence": 84.7,
    "prediction": "1",
    "prode": "1",
    "eloAdvantage": 2.789
  },
  {
    "home": "Colombia",
    "away": "Qatar",
    "homeELO": 1919.9,
    "awayELO": 1589.8,
    "expectedGoals": "3.06 - 0.56",
    "probability_1": 84.7,
    "probability_X": 11.3,
    "probability_2": 3.9,
    "confidence": 84.7,
    "prediction": "1",
    "prode": "1",
    "eloAdvantage": 3.3
  },
  {
    "home": "Australia",
    "away": "Curaçao",
    "homeELO": 1891.1,
    "awayELO": 1597.2,
    "expectedGoals": "2.39 - 0.41",
    "probability_1": 84.7,
    "probability_X": 11.7,
    "probability_2": 3.6,
    "confidence": 84.7,
    "prediction": "1",
    "prode": "1",
    "eloAdvantage": 2.94
  },
  {
    "home": "Mexico",
    "away": "Curaçao",
    "homeELO": 1901.6,
    "awayELO": 1597.2,
    "expectedGoals": "2.39 - 0.42",
    "probability_1": 84.5,
    "probability_X": 11.8,
    "probability_2": 3.7,
    "confidence": 84.5,
    "prediction": "1",
    "prode": "1",
    "eloAdvantage": 3.044
  },
  {
    "home": "Germany",
    "away": "Qatar",
    "homeELO": 1878.7,
    "awayELO": 1589.8,
    "expectedGoals": "3.48 - 0.61",
    "probability_1": 84.3,
    "probability_X": 10.7,
    "probability_2": 5.0,
    "confidence": 84.3,
    "prediction": "1",
    "prode": "1",
    "eloAdvantage": 2.889
  },
  {
    "home": "Argentina",
    "away": "Jordan",
    "homeELO": 2025.5,
    "awayELO": 1703.5,
    "expectedGoals": "2.50 - 0.37",
    "probability_1": 84.2,
    "probability_X": 12.1,
    "probability_2": 3.7,
    "confidence": 84.2,
    "prediction": "1",
    "prode": "1",
    "eloAdvantage": 3.22
  },
  {
    "home": "Spain",
    "away": "Jordan",
    "homeELO": 2006.1,
    "awayELO": 1703.5,
    "expectedGoals": "2.80 - 0.56",
    "probability_1": 84.1,
    "probability_X": 11.9,
    "probability_2": 4.0,
    "confidence": 84.1,
    "prediction": "1",
    "prode": "1",
    "eloAdvantage": 3.027
  },
  {
    "home": "Portugal",
    "away": "Qatar",
    "homeELO": 1889.8,
    "awayELO": 1589.8,
    "expectedGoals": "3.09 - 0.54",
    "probability_1": 83.8,
    "probability_X": 12.1,
    "probability_2": 4.1,
    "confidence": 83.8,
    "prediction": "1",
    "prode": "1",
    "eloAdvantage": 3.0
  },
  {
    "home": "Algeria",
    "away": "Curaçao",
    "homeELO": 1828.7,
    "awayELO": 1597.2,
    "expectedGoals": "2.65 - 0.53",
    "probability_1": 83.3,
    "probability_X": 11.8,
    "probability_2": 4.9,
    "confidence": 83.3,
    "prediction": "1",
    "prode": "1",
    "eloAdvantage": 2.316
  },
  {
    "home": "Spain",
    "away": "Bosnia and Herzegovina",
    "homeELO": 2006.1,
    "awayELO": 1550.2,
    "expectedGoals": "2.26 - 0.45",
    "probability_1": 83.1,
    "probability_X": 13.7,
    "probability_2": 3.2,
    "confidence": 83.1,
    "prediction": "1",
    "prode": "1",
    "eloAdvantage": 4.559
  },
  {
    "home": "Norway",
    "away": "Qatar",
    "homeELO": 1873.2,
    "awayELO": 1589.8,
    "expectedGoals": "3.20 - 0.60",
    "probability_1": 83.1,
    "probability_X": 12.4,
    "probability_2": 4.6,
    "confidence": 83.1,
    "prediction": "1",
    "prode": "1",
    "eloAdvantage": 2.834
  },
  {
    "home": "Croatia",
    "away": "Curaçao",
    "homeELO": 1799.9,
    "awayELO": 1597.2,
    "expectedGoals": "3.04 - 0.52",
    "probability_1": 83.1,
    "probability_X": 10.7,
    "probability_2": 6.2,
    "confidence": 83.1,
    "prediction": "1",
    "prode": "1",
    "eloAdvantage": 2.027
  },
  {
    "home": "Argentina",
    "away": "Bosnia and Herzegovina",
    "homeELO": 2025.5,
    "awayELO": 1550.2,
    "expectedGoals": "2.03 - 0.30",
    "probability_1": 83.0,
    "probability_X": 14.3,
    "probability_2": 2.7,
    "confidence": 83.0,
    "prediction": "1",
    "prode": "1",
    "eloAdvantage": 4.752
  },
  {
    "home": "Spain",
    "away": "Panama",
    "homeELO": 2006.1,
    "awayELO": 1746.6,
    "expectedGoals": "2.73 - 0.46",
    "probability_1": 83.0,
    "probability_X": 12.8,
    "probability_2": 4.2,
    "confidence": 83.0,
    "prediction": "1",
    "prode": "1",
    "eloAdvantage": 2.595
  },
  {
    "home": "Senegal",
    "away": "Curaçao",
    "homeELO": 1834.6,
    "awayELO": 1597.2,
    "expectedGoals": "2.65 - 0.49",
    "probability_1": 83.0,
    "probability_X": 11.9,
    "probability_2": 5.1,
    "confidence": 83.0,
    "prediction": "1",
    "prode": "1",
    "eloAdvantage": 2.374
  },
  {
    "home": "Argentina",
    "away": "Iraq",
    "homeELO": 2025.5,
    "awayELO": 1687.5,
    "expectedGoals": "2.04 - 0.26",
    "probability_1": 82.9,
    "probability_X": 14.1,
    "probability_2": 3.0,
    "confidence": 82.9,
    "prediction": "1",
    "prode": "1",
    "eloAdvantage": 3.38
  },
  {
    "home": "Netherlands",
    "away": "Qatar",
    "homeELO": 1866.5,
    "awayELO": 1589.8,
    "expectedGoals": "3.12 - 0.59",
    "probability_1": 82.9,
    "probability_X": 12.4,
    "probability_2": 4.7,
    "confidence": 82.9,
    "prediction": "1",
    "prode": "1",
    "eloAdvantage": 2.766
  },
  {
    "home": "Argentina",
    "away": "New Zealand",
    "homeELO": 2025.5,
    "awayELO": 1685.3,
    "expectedGoals": "2.15 - 0.27",
    "probability_1": 82.8,
    "probability_X": 13.8,
    "probability_2": 3.4,
    "confidence": 82.8,
    "prediction": "1",
    "prode": "1",
    "eloAdvantage": 3.401
  },
  {
    "home": "Spain",
    "away": "Tunisia",
    "homeELO": 2006.1,
    "awayELO": 1632.0,
    "expectedGoals": "2.23 - 0.46",
    "probability_1": 82.8,
    "probability_X": 13.7,
    "probability_2": 3.5,
    "confidence": 82.8,
    "prediction": "1",
    "prode": "1",
    "eloAdvantage": 3.741
  },
  {
    "home": "Argentina",
    "away": "Tunisia",
    "homeELO": 2025.5,
    "awayELO": 1632.0,
    "expectedGoals": "1.99 - 0.30",
    "probability_1": 82.7,
    "probability_X": 14.3,
    "probability_2": 3.0,
    "confidence": 82.7,
    "prediction": "1",
    "prode": "1",
    "eloAdvantage": 3.935
  },
  {
    "home": "Austria",
    "away": "Curaçao",
    "homeELO": 1784.4,
    "awayELO": 1597.2,
    "expectedGoals": "2.75 - 0.44",
    "probability_1": 82.5,
    "probability_X": 11.7,
    "probability_2": 5.8,
    "confidence": 82.5,
    "prediction": "1",
    "prode": "1",
    "eloAdvantage": 1.872
  },
  {
    "home": "Argentina",
    "away": "Ghana",
    "homeELO": 2025.5,
    "awayELO": 1633.3,
    "expectedGoals": "1.99 - 0.29",
    "probability_1": 82.4,
    "probability_X": 14.5,
    "probability_2": 3.1,
    "confidence": 82.4,
    "prediction": "1",
    "prode": "1",
    "eloAdvantage": 3.922
  },
  {
    "home": "Spain",
    "away": "New Zealand",
    "homeELO": 2006.1,
    "awayELO": 1685.3,
    "expectedGoals": "2.40 - 0.41",
    "probability_1": 82.3,
    "probability_X": 13.9,
    "probability_2": 3.8,
    "confidence": 82.3,
    "prediction": "1",
    "prode": "1",
    "eloAdvantage": 3.208
  },
  {
    "home": "France",
    "away": "Haiti",
    "homeELO": 1997.5,
    "awayELO": 1673.3,
    "expectedGoals": "2.93 - 0.52",
    "probability_1": 82.3,
    "probability_X": 12.8,
    "probability_2": 4.9,
    "confidence": 82.3,
    "prediction": "1",
    "prode": "1",
    "eloAdvantage": 3.241
  },
  {
    "home": "Argentina",
    "away": "Cabo Verde",
    "homeELO": 2025.5,
    "awayELO": 1639.3,
    "expectedGoals": "1.98 - 0.25",
    "probability_1": 82.2,
    "probability_X": 14.8,
    "probability_2": 3.0,
    "confidence": 82.2,
    "prediction": "1",
    "prode": "1",
    "eloAdvantage": 3.861
  },
  {
    "home": "Argentina",
    "away": "South Africa",
    "homeELO": 2025.5,
    "awayELO": 1647.3,
    "expectedGoals": "2.10 - 0.28",
    "probability_1": 82.0,
    "probability_X": 14.8,
    "probability_2": 3.2,
    "confidence": 82.0,
    "prediction": "1",
    "prode": "1",
    "eloAdvantage": 3.781
  },
  {
    "home": "England",
    "away": "Haiti",
    "homeELO": 1969.7,
    "awayELO": 1673.3,
    "expectedGoals": "2.80 - 0.43",
    "probability_1": 81.9,
    "probability_X": 13.5,
    "probability_2": 4.6,
    "confidence": 81.9,
    "prediction": "1",
    "prode": "1",
    "eloAdvantage": 2.964
  },
  {
    "home": "Spain",
    "away": "Ghana",
    "homeELO": 2006.1,
    "awayELO": 1633.3,
    "expectedGoals": "2.23 - 0.44",
    "probability_1": 81.8,
    "probability_X": 14.5,
    "probability_2": 3.7,
    "confidence": 81.8,
    "prediction": "1",
    "prode": "1",
    "eloAdvantage": 3.729
  },
  {
    "home": "Iran",
    "away": "Curaçao",
    "homeELO": 1852.0,
    "awayELO": 1597.2,
    "expectedGoals": "2.51 - 0.60",
    "probability_1": 81.7,
    "probability_X": 12.7,
    "probability_2": 5.6,
    "confidence": 81.7,
    "prediction": "1",
    "prode": "1",
    "eloAdvantage": 2.548
  },
  {
    "home": "Spain",
    "away": "South Africa",
    "homeELO": 2006.1,
    "awayELO": 1647.3,
    "expectedGoals": "2.35 - 0.43",
    "probability_1": 81.3,
    "probability_X": 15.0,
    "probability_2": 3.7,
    "confidence": 81.3,
    "prediction": "1",
    "prode": "1",
    "eloAdvantage": 3.588
  },
  {
    "home": "Turkey",
    "away": "Curaçao",
    "homeELO": 1770.6,
    "awayELO": 1597.2,
    "expectedGoals": "2.92 - 0.60",
    "probability_1": 81.1,
    "probability_X": 12.2,
    "probability_2": 6.7,
    "confidence": 81.1,
    "prediction": "1",
    "prode": "1",
    "eloAdvantage": 1.735
  },
  {
    "home": "Spain",
    "away": "Cabo Verde",
    "homeELO": 2006.1,
    "awayELO": 1639.3,
    "expectedGoals": "2.21 - 0.38",
    "probability_1": 80.9,
    "probability_X": 15.4,
    "probability_2": 3.7,
    "confidence": 80.9,
    "prediction": "1",
    "prode": "1",
    "eloAdvantage": 3.668
  },
  {
    "home": "Brazil",
    "away": "Haiti",
    "homeELO": 1906.3,
    "awayELO": 1673.3,
    "expectedGoals": "2.96 - 0.54",
    "probability_1": 80.8,
    "probability_X": 12.9,
    "probability_2": 6.3,
    "confidence": 80.8,
    "prediction": "1",
    "prode": "1",
    "eloAdvantage": 2.33
  },
  {
    "home": "Spain",
    "away": "Iraq",
    "homeELO": 2006.1,
    "awayELO": 1687.5,
    "expectedGoals": "2.28 - 0.39",
    "probability_1": 80.6,
    "probability_X": 15.5,
    "probability_2": 3.9,
    "confidence": 80.6,
    "prediction": "1",
    "prode": "1",
    "eloAdvantage": 3.186
  },
  {
    "home": "Morocco",
    "away": "Qatar",
    "homeELO": 1950.5,
    "awayELO": 1589.8,
    "expectedGoals": "2.05 - 0.34",
    "probability_1": 80.4,
    "probability_X": 15.7,
    "probability_2": 3.9,
    "confidence": 80.4,
    "prediction": "1",
    "prode": "1",
    "eloAdvantage": 3.607
  },
  {
    "home": "England",
    "away": "Panama",
    "homeELO": 1969.7,
    "awayELO": 1746.6,
    "expectedGoals": "2.39 - 0.45",
    "probability_1": 80.3,
    "probability_X": 14.3,
    "probability_2": 5.4,
    "confidence": 80.3,
    "prediction": "1",
    "prode": "1",
    "eloAdvantage": 2.231
  },
  {
    "home": "United States",
    "away": "Curaçao",
    "homeELO": 1807.7,
    "awayELO": 1597.2,
    "expectedGoals": "2.60 - 0.65",
    "probability_1": 80.3,
    "probability_X": 12.6,
    "probability_2": 7.1,
    "confidence": 80.3,
    "prediction": "1",
    "prode": "1",
    "eloAdvantage": 2.105
  },
  {
    "home": "South Korea",
    "away": "Curaçao",
    "homeELO": 1852.3,
    "awayELO": 1597.2,
    "expectedGoals": "2.40 - 0.58",
    "probability_1": 80.2,
    "probability_X": 13.8,
    "probability_2": 6.0,
    "confidence": 80.2,
    "prediction": "1",
    "prode": "1",
    "eloAdvantage": 2.551
  },
  {
    "home": "Ecuador",
    "away": "Curaçao",
    "homeELO": 1826.0,
    "awayELO": 1597.2,
    "expectedGoals": "1.98 - 0.27",
    "probability_1": 80.2,
    "probability_X": 15.1,
    "probability_2": 4.6,
    "confidence": 80.2,
    "prediction": "1",
    "prode": "1",
    "eloAdvantage": 2.288
  },
  {
    "home": "Argentina",
    "away": "Czech Republic",
    "homeELO": 2025.5,
    "awayELO": 1655.7,
    "expectedGoals": "2.03 - 0.42",
    "probability_1": 79.8,
    "probability_X": 15.7,
    "probability_2": 4.5,
    "confidence": 79.8,
    "prediction": "1",
    "prode": "1",
    "eloAdvantage": 3.698
  },
  {
    "home": "Uruguay",
    "away": "Curaçao",
    "homeELO": 1795.5,
    "awayELO": 1597.2,
    "expectedGoals": "2.17 - 0.35",
    "probability_1": 79.6,
    "probability_X": 14.8,
    "probability_2": 5.6,
    "confidence": 79.6,
    "prediction": "1",
    "prode": "1",
    "eloAdvantage": 1.984
  },
  {
    "home": "France",
    "away": "Panama",
    "homeELO": 1997.5,
    "awayELO": 1746.6,
    "expectedGoals": "2.51 - 0.55",
    "probability_1": 79.5,
    "probability_X": 14.3,
    "probability_2": 6.2,
    "confidence": 79.5,
    "prediction": "1",
    "prode": "1",
    "eloAdvantage": 2.509
  },
  {
    "home": "Germany",
    "away": "Haiti",
    "homeELO": 1878.7,
    "awayELO": 1673.3,
    "expectedGoals": "3.30 - 0.63",
    "probability_1": 79.5,
    "probability_X": 12.5,
    "probability_2": 8.0,
    "confidence": 79.5,
    "prediction": "1",
    "prode": "1",
    "eloAdvantage": 2.054
  },
  {
    "home": "Scotland",
    "away": "Curaçao",
    "homeELO": 1747.6,
    "awayELO": 1597.2,
    "expectedGoals": "2.41 - 0.53",
    "probability_1": 79.5,
    "probability_X": 13.9,
    "probability_2": 6.7,
    "confidence": 79.5,
    "prediction": "1",
    "prode": "1",
    "eloAdvantage": 1.504
  },
  {
    "home": "France",
    "away": "Jordan",
    "homeELO": 1997.5,
    "awayELO": 1703.5,
    "expectedGoals": "2.57 - 0.67",
    "probability_1": 79.4,
    "probability_X": 14.1,
    "probability_2": 6.5,
    "confidence": 79.4,
    "prediction": "1",
    "prode": "1",
    "eloAdvantage": 2.94
  },
  {
    "home": "England",
    "away": "Jordan",
    "homeELO": 1969.7,
    "awayELO": 1703.5,
    "expectedGoals": "2.45 - 0.55",
    "probability_1": 79.4,
    "probability_X": 14.7,
    "probability_2": 5.9,
    "confidence": 79.4,
    "prediction": "1",
    "prode": "1",
    "eloAdvantage": 2.663
  },
  {
    "home": "England",
    "away": "New Zealand",
    "homeELO": 1969.7,
    "awayELO": 1685.3,
    "expectedGoals": "2.11 - 0.40",
    "probability_1": 79.4,
    "probability_X": 15.7,
    "probability_2": 4.9,
    "confidence": 79.4,
    "prediction": "1",
    "prode": "1",
    "eloAdvantage": 2.844
  },
  {
    "home": "England",
    "away": "Bosnia and Herzegovina",
    "homeELO": 1969.7,
    "awayELO": 1550.2,
    "expectedGoals": "1.98 - 0.44",
    "probability_1": 79.4,
    "probability_X": 16.3,
    "probability_2": 4.3,
    "confidence": 79.4,
    "prediction": "1",
    "prode": "1",
    "eloAdvantage": 4.195
  },
  {
    "home": "Japan",
    "away": "Qatar",
    "homeELO": 1923.1,
    "awayELO": 1589.8,
    "expectedGoals": "2.48 - 0.48",
    "probability_1": 79.4,
    "probability_X": 15.7,
    "probability_2": 4.9,
    "confidence": 79.4,
    "prediction": "1",
    "prode": "1",
    "eloAdvantage": 3.332
  },
  {
    "home": "Sweden",
    "away": "Curaçao",
    "homeELO": 1701.6,
    "awayELO": 1597.2,
    "expectedGoals": "3.26 - 0.72",
    "probability_1": 79.4,
    "probability_X": 11.1,
    "probability_2": 9.6,
    "confidence": 79.4,
    "prediction": "1",
    "prode": "1",
    "eloAdvantage": 1.045
  },
  {
    "home": "Colombia",
    "away": "Haiti",
    "homeELO": 1919.9,
    "awayELO": 1673.3,
    "expectedGoals": "2.90 - 0.57",
    "probability_1": 79.1,
    "probability_X": 14.2,
    "probability_2": 6.7,
    "confidence": 79.1,
    "prediction": "1",
    "prode": "1",
    "eloAdvantage": 2.465
  },
  {
    "home": "England",
    "away": "Tunisia",
    "homeELO": 1969.7,
    "awayELO": 1632.0,
    "expectedGoals": "1.95 - 0.45",
    "probability_1": 79.0,
    "probability_X": 16.3,
    "probability_2": 4.7,
    "confidence": 79.0,
    "prediction": "1",
    "prode": "1",
    "eloAdvantage": 3.377
  },
  {
    "home": "France",
    "away": "New Zealand",
    "homeELO": 1997.5,
    "awayELO": 1685.3,
    "expectedGoals": "2.21 - 0.48",
    "probability_1": 78.7,
    "probability_X": 15.6,
    "probability_2": 5.7,
    "confidence": 78.7,
    "prediction": "1",
    "prode": "1",
    "eloAdvantage": 3.121
  },
  {
    "home": "France",
    "away": "Bosnia and Herzegovina",
    "homeELO": 1997.5,
    "awayELO": 1550.2,
    "expectedGoals": "2.08 - 0.54",
    "probability_1": 78.7,
    "probability_X": 16.3,
    "probability_2": 5.1,
    "confidence": 78.7,
    "prediction": "1",
    "prode": "1",
    "eloAdvantage": 4.472
  },
  {
    "home": "Spain",
    "away": "Czech Republic",
    "homeELO": 2006.1,
    "awayELO": 1655.7,
    "expectedGoals": "2.27 - 0.64",
    "probability_1": 78.6,
    "probability_X": 15.7,
    "probability_2": 5.7,
    "confidence": 78.6,
    "prediction": "1",
    "prode": "1",
    "eloAdvantage": 3.504
  },
  {
    "home": "France",
    "away": "South Africa",
    "homeELO": 1997.5,
    "awayELO": 1647.3,
    "expectedGoals": "2.15 - 0.51",
    "probability_1": 78.6,
    "probability_X": 16.1,
    "probability_2": 5.3,
    "confidence": 78.6,
    "prediction": "1",
    "prode": "1",
    "eloAdvantage": 3.501
  },
  {
    "home": "Argentina",
    "away": "Sweden",
    "homeELO": 2025.5,
    "awayELO": 1701.6,
    "expectedGoals": "2.15 - 0.57",
    "probability_1": 78.3,
    "probability_X": 15.9,
    "probability_2": 5.8,
    "confidence": 78.3,
    "prediction": "1",
    "prode": "1",
    "eloAdvantage": 3.239
  },
  {
    "home": "Norway",
    "away": "Haiti",
    "homeELO": 1873.2,
    "awayELO": 1673.3,
    "expectedGoals": "3.03 - 0.62",
    "probability_1": 78.3,
    "probability_X": 14.5,
    "probability_2": 7.1,
    "confidence": 78.3,
    "prediction": "1",
    "prode": "1",
    "eloAdvantage": 1.999
  },
  {
    "home": "Belgium",
    "away": "Qatar",
    "homeELO": 1804.6,
    "awayELO": 1589.8,
    "expectedGoals": "2.70 - 0.59",
    "probability_1": 78.3,
    "probability_X": 14.9,
    "probability_2": 6.8,
    "confidence": 78.3,
    "prediction": "1",
    "prode": "1",
    "eloAdvantage": 2.147
  },
  {
    "home": "Spain",
    "away": "Saudi Arabia",
    "homeELO": 2006.1,
    "awayELO": 1690.8,
    "expectedGoals": "2.14 - 0.40",
    "probability_1": 78.2,
    "probability_X": 17.1,
    "probability_2": 4.7,
    "confidence": 78.2,
    "prediction": "1",
    "prode": "1",
    "eloAdvantage": 3.153
  },
  {
    "home": "France",
    "away": "Cabo Verde",
    "homeELO": 1997.5,
    "awayELO": 1639.3,
    "expectedGoals": "2.03 - 0.45",
    "probability_1": 78.2,
    "probability_X": 16.6,
    "probability_2": 5.3,
    "confidence": 78.2,
    "prediction": "1",
    "prode": "1",
    "eloAdvantage": 3.581
  },
  {
    "home": "Germany",
    "away": "Bosnia and Herzegovina",
    "homeELO": 1878.7,
    "awayELO": 1550.2,
    "expectedGoals": "2.34 - 0.66",
    "probability_1": 78.1,
    "probability_X": 15.3,
    "probability_2": 6.6,
    "confidence": 78.1,
    "prediction": "1",
    "prode": "1",
    "eloAdvantage": 3.285
  },
  {
    "home": "France",
    "away": "Iraq",
    "homeELO": 1997.5,
    "awayELO": 1687.5,
    "expectedGoals": "2.09 - 0.47",
    "probability_1": 78.0,
    "probability_X": 16.5,
    "probability_2": 5.5,
    "confidence": 78.0,
    "prediction": "1",
    "prode": "1",
    "eloAdvantage": 3.1
  },
  {
    "home": "Portugal",
    "away": "Haiti",
    "homeELO": 1889.8,
    "awayELO": 1673.3,
    "expectedGoals": "2.93 - 0.56",
    "probability_1": 78.0,
    "probability_X": 15.1,
    "probability_2": 6.9,
    "confidence": 78.0,
    "prediction": "1",
    "prode": "1",
    "eloAdvantage": 2.165
  },
  {
    "home": "France",
    "away": "Ghana",
    "homeELO": 1997.5,
    "awayELO": 1633.3,
    "expectedGoals": "2.04 - 0.53",
    "probability_1": 77.9,
    "probability_X": 16.4,
    "probability_2": 5.6,
    "confidence": 77.9,
    "prediction": "1",
    "prode": "1",
    "eloAdvantage": 3.642
  },
  {
    "home": "England",
    "away": "Cabo Verde",
    "homeELO": 1969.7,
    "awayELO": 1639.3,
    "expectedGoals": "1.93 - 0.37",
    "probability_1": 77.9,
    "probability_X": 17.3,
    "probability_2": 4.8,
    "confidence": 77.9,
    "prediction": "1",
    "prode": "1",
    "eloAdvantage": 3.304
  },
  {
    "home": "Canada",
    "away": "Curaçao",
    "homeELO": 1794.1,
    "awayELO": 1597.2,
    "expectedGoals": "2.11 - 0.48",
    "probability_1": 77.9,
    "probability_X": 15.7,
    "probability_2": 6.4,
    "confidence": 77.9,
    "prediction": "1",
    "prode": "1",
    "eloAdvantage": 1.97
  },
  {
    "home": "Argentina",
    "away": "Saudi Arabia",
    "homeELO": 2025.5,
    "awayELO": 1690.8,
    "expectedGoals": "1.92 - 0.26",
    "probability_1": 77.8,
    "probability_X": 17.8,
    "probability_2": 4.4,
    "confidence": 77.8,
    "prediction": "1",
    "prode": "1",
    "eloAdvantage": 3.347
  },
  {
    "home": "England",
    "away": "Ghana",
    "homeELO": 1969.7,
    "awayELO": 1633.3,
    "expectedGoals": "1.95 - 0.43",
    "probability_1": 77.8,
    "probability_X": 17.1,
    "probability_2": 5.0,
    "confidence": 77.8,
    "prediction": "1",
    "prode": "1",
    "eloAdvantage": 3.365
  },
  {
    "home": "England",
    "away": "Iraq",
    "homeELO": 1969.7,
    "awayELO": 1687.5,
    "expectedGoals": "2.00 - 0.39",
    "probability_1": 77.7,
    "probability_X": 17.3,
    "probability_2": 5.0,
    "confidence": 77.7,
    "prediction": "1",
    "prode": "1",
    "eloAdvantage": 2.822
  },
  {
    "home": "England",
    "away": "South Africa",
    "homeELO": 1969.7,
    "awayELO": 1647.3,
    "expectedGoals": "2.05 - 0.42",
    "probability_1": 77.5,
    "probability_X": 17.5,
    "probability_2": 5.0,
    "confidence": 77.5,
    "prediction": "1",
    "prode": "1",
    "eloAdvantage": 3.224
  },
  {
    "home": "Ivory Coast",
    "away": "Curaçao",
    "homeELO": 1830.5,
    "awayELO": 1597.2,
    "expectedGoals": "1.99 - 0.42",
    "probability_1": 77.5,
    "probability_X": 16.2,
    "probability_2": 6.3,
    "confidence": 77.5,
    "prediction": "1",
    "prode": "1",
    "eloAdvantage": 2.333
  },
  {
    "home": "France",
    "away": "Tunisia",
    "homeELO": 1997.5,
    "awayELO": 1632.0,
    "expectedGoals": "2.04 - 0.55",
    "probability_1": 77.3,
    "probability_X": 16.8,
    "probability_2": 5.8,
    "confidence": 77.3,
    "prediction": "1",
    "prode": "1",
    "eloAdvantage": 3.655
  },
  {
    "home": "Colombia",
    "away": "Panama",
    "homeELO": 1919.9,
    "awayELO": 1746.6,
    "expectedGoals": "2.48 - 0.61",
    "probability_1": 77.2,
    "probability_X": 15.1,
    "probability_2": 7.8,
    "confidence": 77.2,
    "prediction": "1",
    "prode": "1",
    "eloAdvantage": 1.733
  },
  {
    "home": "Germany",
    "away": "Ghana",
    "homeELO": 1878.7,
    "awayELO": 1633.3,
    "expectedGoals": "2.30 - 0.64",
    "probability_1": 77.2,
    "probability_X": 15.3,
    "probability_2": 7.6,
    "confidence": 77.2,
    "prediction": "1",
    "prode": "1",
    "eloAdvantage": 2.454
  },
  {
    "home": "Colombia",
    "away": "Jordan",
    "homeELO": 1919.9,
    "awayELO": 1703.5,
    "expectedGoals": "2.54 - 0.74",
    "probability_1": 76.9,
    "probability_X": 14.9,
    "probability_2": 8.1,
    "confidence": 76.9,
    "prediction": "1",
    "prode": "1",
    "eloAdvantage": 2.164
  },
  {
    "home": "Netherlands",
    "away": "Haiti",
    "homeELO": 1866.5,
    "awayELO": 1673.3,
    "expectedGoals": "2.95 - 0.61",
    "probability_1": 76.9,
    "probability_X": 15.2,
    "probability_2": 7.9,
    "confidence": 76.9,
    "prediction": "1",
    "prode": "1",
    "eloAdvantage": 1.931
  },
  {
    "home": "Brazil",
    "away": "Panama",
    "homeELO": 1906.3,
    "awayELO": 1746.6,
    "expectedGoals": "2.53 - 0.57",
    "probability_1": 76.8,
    "probability_X": 15.0,
    "probability_2": 8.3,
    "confidence": 76.8,
    "prediction": "1",
    "prode": "1",
    "eloAdvantage": 1.597
  },
  {
    "home": "Brazil",
    "away": "Jordan",
    "homeELO": 1906.3,
    "awayELO": 1703.5,
    "expectedGoals": "2.59 - 0.70",
    "probability_1": 76.7,
    "probability_X": 14.8,
    "probability_2": 8.4,
    "confidence": 76.7,
    "prediction": "1",
    "prode": "1",
    "eloAdvantage": 2.028
  },
  {
    "home": "Brazil",
    "away": "Ghana",
    "homeELO": 1906.3,
    "awayELO": 1633.3,
    "expectedGoals": "2.06 - 0.55",
    "probability_1": 76.7,
    "probability_X": 16.6,
    "probability_2": 6.7,
    "confidence": 76.7,
    "prediction": "1",
    "prode": "1",
    "eloAdvantage": 2.73
  },
  {
    "home": "Germany",
    "away": "Panama",
    "homeELO": 1878.7,
    "awayELO": 1746.6,
    "expectedGoals": "2.82 - 0.67",
    "probability_1": 76.7,
    "probability_X": 13.7,
    "probability_2": 9.6,
    "confidence": 76.7,
    "prediction": "1",
    "prode": "1",
    "eloAdvantage": 1.321
  },
  {
    "home": "Brazil",
    "away": "Bosnia and Herzegovina",
    "homeELO": 1906.3,
    "awayELO": 1550.2,
    "expectedGoals": "2.10 - 0.56",
    "probability_1": 76.6,
    "probability_X": 17.2,
    "probability_2": 6.2,
    "confidence": 76.6,
    "prediction": "1",
    "prode": "1",
    "eloAdvantage": 3.561
  },
  {
    "home": "Germany",
    "away": "Jordan",
    "homeELO": 1878.7,
    "awayELO": 1703.5,
    "expectedGoals": "2.89 - 0.82",
    "probability_1": 76.6,
    "probability_X": 13.7,
    "probability_2": 9.7,
    "confidence": 76.6,
    "prediction": "1",
    "prode": "1",
    "eloAdvantage": 1.752
  },
  {
    "home": "Germany",
    "away": "Tunisia",
    "homeELO": 1878.7,
    "awayELO": 1632.0,
    "expectedGoals": "2.30 - 0.67",
    "probability_1": 76.5,
    "probability_X": 15.7,
    "probability_2": 7.7,
    "confidence": 76.5,
    "prediction": "1",
    "prode": "1",
    "eloAdvantage": 2.467
  },
  {
    "home": "Norway",
    "away": "Panama",
    "homeELO": 1873.2,
    "awayELO": 1746.6,
    "expectedGoals": "2.59 - 0.65",
    "probability_1": 76.5,
    "probability_X": 15.2,
    "probability_2": 8.3,
    "confidence": 76.5,
    "prediction": "1",
    "prode": "1",
    "eloAdvantage": 1.266
  },
  {
    "home": "Colombia",
    "away": "New Zealand",
    "homeELO": 1919.9,
    "awayELO": 1685.3,
    "expectedGoals": "2.19 - 0.53",
    "probability_1": 76.4,
    "probability_X": 16.4,
    "probability_2": 7.1,
    "confidence": 76.4,
    "prediction": "1",
    "prode": "1",
    "eloAdvantage": 2.345
  },
  {
    "home": "Germany",
    "away": "New Zealand",
    "homeELO": 1878.7,
    "awayELO": 1685.3,
    "expectedGoals": "2.49 - 0.59",
    "probability_1": 76.4,
    "probability_X": 15.0,
    "probability_2": 8.7,
    "confidence": 76.4,
    "prediction": "1",
    "prode": "1",
    "eloAdvantage": 1.934
  },
  {
    "home": "Germany",
    "away": "Cabo Verde",
    "homeELO": 1878.7,
    "awayELO": 1639.3,
    "expectedGoals": "2.28 - 0.55",
    "probability_1": 76.3,
    "probability_X": 15.9,
    "probability_2": 7.8,
    "confidence": 76.3,
    "prediction": "1",
    "prode": "1",
    "eloAdvantage": 2.394
  },
  {
    "home": "Norway",
    "away": "Jordan",
    "homeELO": 1873.2,
    "awayELO": 1703.5,
    "expectedGoals": "2.66 - 0.79",
    "probability_1": 76.2,
    "probability_X": 15.1,
    "probability_2": 8.7,
    "confidence": 76.2,
    "prediction": "1",
    "prode": "1",
    "eloAdvantage": 1.697
  },
  {
    "home": "Brazil",
    "away": "New Zealand",
    "homeELO": 1906.3,
    "awayELO": 1685.3,
    "expectedGoals": "2.23 - 0.50",
    "probability_1": 76.1,
    "probability_X": 16.4,
    "probability_2": 7.5,
    "confidence": 76.1,
    "prediction": "1",
    "prode": "1",
    "eloAdvantage": 2.21
  },
  {
    "home": "Brazil",
    "away": "Tunisia",
    "homeELO": 1906.3,
    "awayELO": 1632.0,
    "expectedGoals": "2.06 - 0.57",
    "probability_1": 76.1,
    "probability_X": 17.1,
    "probability_2": 6.9,
    "confidence": 76.1,
    "prediction": "1",
    "prode": "1",
    "eloAdvantage": 2.743
  },
  {
    "home": "Argentina",
    "away": "United States",
    "homeELO": 2025.5,
    "awayELO": 1807.7,
    "expectedGoals": "1.96 - 0.45",
    "probability_1": 75.9,
    "probability_X": 17.4,
    "probability_2": 6.7,
    "confidence": 75.9,
    "prediction": "1",
    "prode": "1",
    "eloAdvantage": 2.178
  },
  {
    "home": "Morocco",
    "away": "Haiti",
    "homeELO": 1950.5,
    "awayELO": 1673.3,
    "expectedGoals": "1.95 - 0.35",
    "probability_1": 75.9,
    "probability_X": 18.3,
    "probability_2": 5.8,
    "confidence": 75.9,
    "prediction": "1",
    "prode": "1",
    "eloAdvantage": 2.772
  },
  {
    "home": "Portugal",
    "away": "Bosnia and Herzegovina",
    "homeELO": 1889.8,
    "awayELO": 1550.2,
    "expectedGoals": "2.07 - 0.58",
    "probability_1": 75.9,
    "probability_X": 17.9,
    "probability_2": 6.2,
    "confidence": 75.9,
    "prediction": "1",
    "prode": "1",
    "eloAdvantage": 3.396
  },
  {
    "home": "Germany",
    "away": "Iraq",
    "homeELO": 1878.7,
    "awayELO": 1687.5,
    "expectedGoals": "2.36 - 0.57",
    "probability_1": 75.9,
    "probability_X": 15.9,
    "probability_2": 8.2,
    "confidence": 75.9,
    "prediction": "1",
    "prode": "1",
    "eloAdvantage": 1.912
  },
  {
    "home": "Brazil",
    "away": "Cabo Verde",
    "homeELO": 1906.3,
    "awayELO": 1639.3,
    "expectedGoals": "2.04 - 0.47",
    "probability_1": 75.8,
    "probability_X": 17.4,
    "probability_2": 6.8,
    "confidence": 75.8,
    "prediction": "1",
    "prode": "1",
    "eloAdvantage": 2.67
  },
  {
    "home": "Spain",
    "away": "Sweden",
    "homeELO": 2006.1,
    "awayELO": 1701.6,
    "expectedGoals": "2.40 - 0.87",
    "probability_1": 75.7,
    "probability_X": 16.5,
    "probability_2": 7.7,
    "confidence": 75.7,
    "prediction": "1",
    "prode": "1",
    "eloAdvantage": 3.045
  },
  {
    "home": "Colombia",
    "away": "Iraq",
    "homeELO": 1919.9,
    "awayELO": 1687.5,
    "expectedGoals": "2.07 - 0.52",
    "probability_1": 75.7,
    "probability_X": 17.4,
    "probability_2": 6.9,
    "confidence": 75.7,
    "prediction": "1",
    "prode": "1",
    "eloAdvantage": 2.324
  },
  {
    "home": "Colombia",
    "away": "Bosnia and Herzegovina",
    "homeELO": 1919.9,
    "awayELO": 1550.2,
    "expectedGoals": "2.06 - 0.60",
    "probability_1": 75.6,
    "probability_X": 17.9,
    "probability_2": 6.5,
    "confidence": 75.6,
    "prediction": "1",
    "prode": "1",
    "eloAdvantage": 3.696
  },
  {
    "home": "Portugal",
    "away": "New Zealand",
    "homeELO": 1889.8,
    "awayELO": 1685.3,
    "expectedGoals": "2.20 - 0.52",
    "probability_1": 75.6,
    "probability_X": 17.2,
    "probability_2": 7.3,
    "confidence": 75.6,
    "prediction": "1",
    "prode": "1",
    "eloAdvantage": 2.045
  },
  {
    "home": "Germany",
    "away": "South Africa",
    "homeELO": 1878.7,
    "awayELO": 1647.3,
    "expectedGoals": "2.42 - 0.62",
    "probability_1": 75.6,
    "probability_X": 16.3,
    "probability_2": 8.1,
    "confidence": 75.6,
    "prediction": "1",
    "prode": "1",
    "eloAdvantage": 2.314
  },
  {
    "home": "Brazil",
    "away": "Iraq",
    "homeELO": 1906.3,
    "awayELO": 1687.5,
    "expectedGoals": "2.11 - 0.49",
    "probability_1": 75.5,
    "probability_X": 17.4,
    "probability_2": 7.1,
    "confidence": 75.5,
    "prediction": "1",
    "prode": "1",
    "eloAdvantage": 2.188
  },
  {
    "home": "Brazil",
    "away": "South Africa",
    "homeELO": 1906.3,
    "awayELO": 1647.3,
    "expectedGoals": "2.17 - 0.53",
    "probability_1": 75.3,
    "probability_X": 17.6,
    "probability_2": 7.1,
    "confidence": 75.3,
    "prediction": "1",
    "prode": "1",
    "eloAdvantage": 2.59
  },
  {
    "home": "Norway",
    "away": "Iraq",
    "homeELO": 1873.2,
    "awayELO": 1687.5,
    "expectedGoals": "2.16 - 0.56",
    "probability_1": 75.2,
    "probability_X": 17.5,
    "probability_2": 7.3,
    "confidence": 75.2,
    "prediction": "1",
    "prode": "1",
    "eloAdvantage": 1.857
  },
  {
    "home": "Colombia",
    "away": "Tunisia",
    "homeELO": 1919.9,
    "awayELO": 1632.0,
    "expectedGoals": "2.03 - 0.60",
    "probability_1": 75.1,
    "probability_X": 17.8,
    "probability_2": 7.2,
    "confidence": 75.1,
    "prediction": "1",
    "prode": "1",
    "eloAdvantage": 2.879
  },
  {
    "home": "Portugal",
    "away": "Panama",
    "homeELO": 1889.8,
    "awayELO": 1746.6,
    "expectedGoals": "2.50 - 0.59",
    "probability_1": 75.1,
    "probability_X": 16.4,
    "probability_2": 8.5,
    "confidence": 75.1,
    "prediction": "1",
    "prode": "1",
    "eloAdvantage": 1.432
  },
  {
    "home": "Norway",
    "away": "Bosnia and Herzegovina",
    "homeELO": 1873.2,
    "awayELO": 1550.2,
    "expectedGoals": "2.15 - 0.64",
    "probability_1": 75.1,
    "probability_X": 18.0,
    "probability_2": 6.9,
    "confidence": 75.1,
    "prediction": "1",
    "prode": "1",
    "eloAdvantage": 3.23
  },
  {
    "home": "Colombia",
    "away": "Cabo Verde",
    "homeELO": 1919.9,
    "awayELO": 1639.3,
    "expectedGoals": "2.01 - 0.50",
    "probability_1": 75.0,
    "probability_X": 18.1,
    "probability_2": 6.9,
    "confidence": 75.0,
    "prediction": "1",
    "prode": "1",
    "eloAdvantage": 2.805
  },
  {
    "home": "Portugal",
    "away": "Jordan",
    "homeELO": 1889.8,
    "awayELO": 1703.5,
    "expectedGoals": "2.56 - 0.72",
    "probability_1": 75.0,
    "probability_X": 16.3,
    "probability_2": 8.7,
    "confidence": 75.0,
    "prediction": "1",
    "prode": "1",
    "eloAdvantage": 1.864
  },
  {
    "home": "Portugal",
    "away": "Ghana",
    "homeELO": 1889.8,
    "awayELO": 1633.3,
    "expectedGoals": "2.04 - 0.57",
    "probability_1": 75.0,
    "probability_X": 18.0,
    "probability_2": 7.0,
    "confidence": 75.0,
    "prediction": "1",
    "prode": "1",
    "eloAdvantage": 2.566
  },
  {
    "home": "Colombia",
    "away": "Ghana",
    "homeELO": 1919.9,
    "awayELO": 1633.3,
    "expectedGoals": "2.02 - 0.58",
    "probability_1": 74.8,
    "probability_X": 17.9,
    "probability_2": 7.3,
    "confidence": 74.8,
    "prediction": "1",
    "prode": "1",
    "eloAdvantage": 2.866
  },
  {
    "home": "Switzerland",
    "away": "Qatar",
    "homeELO": 1783.1,
    "awayELO": 1589.8,
    "expectedGoals": "2.52 - 0.59",
    "probability_1": 74.6,
    "probability_X": 17.2,
    "probability_2": 8.2,
    "confidence": 74.6,
    "prediction": "1",
    "prode": "1",
    "eloAdvantage": 1.933
  },
  {
    "home": "Norway",
    "away": "Tunisia",
    "homeELO": 1873.2,
    "awayELO": 1632.0,
    "expectedGoals": "2.11 - 0.65",
    "probability_1": 74.5,
    "probability_X": 17.9,
    "probability_2": 7.6,
    "confidence": 74.5,
    "prediction": "1",
    "prode": "1",
    "eloAdvantage": 2.412
  },
  {
    "home": "Japan",
    "away": "Haiti",
    "homeELO": 1923.1,
    "awayELO": 1673.3,
    "expectedGoals": "2.35 - 0.50",
    "probability_1": 74.4,
    "probability_X": 18.2,
    "probability_2": 7.4,
    "confidence": 74.4,
    "prediction": "1",
    "prode": "1",
    "eloAdvantage": 2.497
  },
  {
    "home": "Colombia",
    "away": "South Africa",
    "homeELO": 1919.9,
    "awayELO": 1647.3,
    "expectedGoals": "2.13 - 0.57",
    "probability_1": 74.4,
    "probability_X": 18.3,
    "probability_2": 7.3,
    "confidence": 74.4,
    "prediction": "1",
    "prode": "1",
    "eloAdvantage": 2.725
  },
  {
    "home": "Norway",
    "away": "Cabo Verde",
    "homeELO": 1873.2,
    "awayELO": 1639.3,
    "expectedGoals": "2.10 - 0.54",
    "probability_1": 74.4,
    "probability_X": 18.2,
    "probability_2": 7.4,
    "confidence": 74.4,
    "prediction": "1",
    "prode": "1",
    "eloAdvantage": 2.339
  },
  {
    "home": "Egypt",
    "away": "Curaçao",
    "homeELO": 1790.0,
    "awayELO": 1597.2,
    "expectedGoals": "1.83 - 0.46",
    "probability_1": 74.3,
    "probability_X": 18.5,
    "probability_2": 7.2,
    "confidence": 74.3,
    "prediction": "1",
    "prode": "1",
    "eloAdvantage": 1.928
  },
  {
    "home": "France",
    "away": "Saudi Arabia",
    "homeELO": 1997.5,
    "awayELO": 1690.8,
    "expectedGoals": "1.96 - 0.47",
    "probability_1": 74.2,
    "probability_X": 18.9,
    "probability_2": 6.9,
    "confidence": 74.2,
    "prediction": "1",
    "prode": "1",
    "eloAdvantage": 3.067
  },
  {
    "home": "England",
    "away": "Czech Republic",
    "homeELO": 1969.7,
    "awayELO": 1655.7,
    "expectedGoals": "1.98 - 0.63",
    "probability_1": 74.2,
    "probability_X": 18.3,
    "probability_2": 7.5,
    "confidence": 74.2,
    "prediction": "1",
    "prode": "1",
    "eloAdvantage": 3.14
  },
  {
    "home": "Norway",
    "away": "Ghana",
    "homeELO": 1873.2,
    "awayELO": 1633.3,
    "expectedGoals": "2.11 - 0.63",
    "probability_1": 74.2,
    "probability_X": 18.1,
    "probability_2": 7.8,
    "confidence": 74.2,
    "prediction": "1",
    "prode": "1",
    "eloAdvantage": 2.399
  },
  {
    "home": "England",
    "away": "Saudi Arabia",
    "homeELO": 1969.7,
    "awayELO": 1690.8,
    "expectedGoals": "1.87 - 0.39",
    "probability_1": 73.9,
    "probability_X": 19.8,
    "probability_2": 6.3,
    "confidence": 73.9,
    "prediction": "1",
    "prode": "1",
    "eloAdvantage": 2.789
  },
  {
    "home": "Australia",
    "away": "Qatar",
    "homeELO": 1891.1,
    "awayELO": 1589.8,
    "expectedGoals": "1.94 - 0.52",
    "probability_1": 73.9,
    "probability_X": 19.4,
    "probability_2": 6.7,
    "confidence": 73.9,
    "prediction": "1",
    "prode": "1",
    "eloAdvantage": 3.013
  },
  {
    "home": "Portugal",
    "away": "Iraq",
    "homeELO": 1889.8,
    "awayELO": 1687.5,
    "expectedGoals": "2.09 - 0.50",
    "probability_1": 73.8,
    "probability_X": 18.8,
    "probability_2": 7.3,
    "confidence": 73.8,
    "prediction": "1",
    "prode": "1",
    "eloAdvantage": 2.023
  },
  {
    "home": "Netherlands",
    "away": "Panama",
    "homeELO": 1866.5,
    "awayELO": 1746.6,
    "expectedGoals": "2.53 - 0.65",
    "probability_1": 73.8,
    "probability_X": 16.6,
    "probability_2": 9.7,
    "confidence": 73.8,
    "prediction": "1",
    "prode": "1",
    "eloAdvantage": 1.199
  },
  {
    "home": "Norway",
    "away": "South Africa",
    "homeELO": 1873.2,
    "awayELO": 1647.3,
    "expectedGoals": "2.23 - 0.61",
    "probability_1": 73.7,
    "probability_X": 18.5,
    "probability_2": 7.7,
    "confidence": 73.7,
    "prediction": "1",
    "prode": "1",
    "eloAdvantage": 2.259
  },
  {
    "home": "Netherlands",
    "away": "Bosnia and Herzegovina",
    "homeELO": 1866.5,
    "awayELO": 1550.2,
    "expectedGoals": "2.09 - 0.64",
    "probability_1": 73.7,
    "probability_X": 18.9,
    "probability_2": 7.4,
    "confidence": 73.7,
    "prediction": "1",
    "prode": "1",
    "eloAdvantage": 3.162
  },
  {
    "home": "Senegal",
    "away": "Qatar",
    "homeELO": 1834.6,
    "awayELO": 1589.8,
    "expectedGoals": "2.15 - 0.63",
    "probability_1": 73.7,
    "probability_X": 18.3,
    "probability_2": 8.0,
    "confidence": 73.7,
    "prediction": "1",
    "prode": "1",
    "eloAdvantage": 2.447
  },
  {
    "home": "Norway",
    "away": "New Zealand",
    "homeELO": 1873.2,
    "awayELO": 1685.3,
    "expectedGoals": "2.28 - 0.57",
    "probability_1": 73.6,
    "probability_X": 17.9,
    "probability_2": 8.5,
    "confidence": 73.6,
    "prediction": "1",
    "prode": "1",
    "eloAdvantage": 1.879
  },
  {
    "home": "France",
    "away": "Czech Republic",
    "homeELO": 1997.5,
    "awayELO": 1655.7,
    "expectedGoals": "2.08 - 0.76",
    "probability_1": 73.5,
    "probability_X": 17.9,
    "probability_2": 8.7,
    "confidence": 73.5,
    "prediction": "1",
    "prode": "1",
    "eloAdvantage": 3.418
  },
  {
    "home": "Portugal",
    "away": "South Africa",
    "homeELO": 1889.8,
    "awayELO": 1647.3,
    "expectedGoals": "2.15 - 0.55",
    "probability_1": 73.5,
    "probability_X": 19.2,
    "probability_2": 7.3,
    "confidence": 73.5,
    "prediction": "1",
    "prode": "1",
    "eloAdvantage": 2.425
  },
  {
    "home": "Netherlands",
    "away": "Jordan",
    "homeELO": 1866.5,
    "awayELO": 1703.5,
    "expectedGoals": "2.59 - 0.79",
    "probability_1": 73.5,
    "probability_X": 16.5,
    "probability_2": 10.0,
    "confidence": 73.5,
    "prediction": "1",
    "prode": "1",
    "eloAdvantage": 1.63
  },
  {
    "home": "Portugal",
    "away": "Tunisia",
    "homeELO": 1889.8,
    "awayELO": 1632.0,
    "expectedGoals": "2.04 - 0.59",
    "probability_1": 73.3,
    "probability_X": 19.2,
    "probability_2": 7.5,
    "confidence": 73.3,
    "prediction": "1",
    "prode": "1",
    "eloAdvantage": 2.578
  },
  {
    "home": "Croatia",
    "away": "Qatar",
    "homeELO": 1799.9,
    "awayELO": 1589.8,
    "expectedGoals": "2.46 - 0.67",
    "probability_1": 73.3,
    "probability_X": 17.3,
    "probability_2": 9.4,
    "confidence": 73.3,
    "prediction": "1",
    "prode": "1",
    "eloAdvantage": 2.1
  },
  {
    "home": "Netherlands",
    "away": "New Zealand",
    "homeELO": 1866.5,
    "awayELO": 1685.3,
    "expectedGoals": "2.22 - 0.57",
    "probability_1": 73.2,
    "probability_X": 18.0,
    "probability_2": 8.8,
    "confidence": 73.2,
    "prediction": "1",
    "prode": "1",
    "eloAdvantage": 1.811
  },
  {
    "home": "Argentina",
    "away": "Uzbekistan",
    "homeELO": 2025.5,
    "awayELO": 1767.1,
    "expectedGoals": "1.65 - 0.30",
    "probability_1": 73.1,
    "probability_X": 20.9,
    "probability_2": 6.0,
    "confidence": 73.1,
    "prediction": "1",
    "prode": "1",
    "eloAdvantage": 2.584
  },
  {
    "home": "Morocco",
    "away": "Jordan",
    "homeELO": 1950.5,
    "awayELO": 1703.5,
    "expectedGoals": "1.71 - 0.46",
    "probability_1": 73.1,
    "probability_X": 19.6,
    "probability_2": 7.2,
    "confidence": 73.1,
    "prediction": "1",
    "prode": "1",
    "eloAdvantage": 2.471
  },
  {
    "home": "Japan",
    "away": "Panama",
    "homeELO": 1923.1,
    "awayELO": 1746.6,
    "expectedGoals": "2.01 - 0.53",
    "probability_1": 73.1,
    "probability_X": 18.7,
    "probability_2": 8.3,
    "confidence": 73.1,
    "prediction": "1",
    "prode": "1",
    "eloAdvantage": 1.765
  },
  {
    "home": "Netherlands",
    "away": "Tunisia",
    "homeELO": 1866.5,
    "awayELO": 1632.0,
    "expectedGoals": "2.06 - 0.65",
    "probability_1": 73.1,
    "probability_X": 18.7,
    "probability_2": 8.2,
    "confidence": 73.1,
    "prediction": "1",
    "prode": "1",
    "eloAdvantage": 2.345
  },
  {
    "home": "Spain",
    "away": "United States",
    "homeELO": 2006.1,
    "awayELO": 1807.7,
    "expectedGoals": "2.19 - 0.69",
    "probability_1": 73.0,
    "probability_X": 18.4,
    "probability_2": 8.6,
    "confidence": 73.0,
    "prediction": "1",
    "prode": "1",
    "eloAdvantage": 1.984
  },
  {
    "home": "Portugal",
    "away": "Cabo Verde",
    "homeELO": 1889.8,
    "awayELO": 1639.3,
    "expectedGoals": "2.02 - 0.49",
    "probability_1": 73.0,
    "probability_X": 19.5,
    "probability_2": 7.4,
    "confidence": 73.0,
    "prediction": "1",
    "prode": "1",
    "eloAdvantage": 2.505
  },
  {
    "home": "Netherlands",
    "away": "Cabo Verde",
    "homeELO": 1866.5,
    "awayELO": 1639.3,
    "expectedGoals": "2.04 - 0.53",
    "probability_1": 73.0,
    "probability_X": 19.0,
    "probability_2": 8.0,
    "confidence": 73.0,
    "prediction": "1",
    "prode": "1",
    "eloAdvantage": 2.271
  },
  {
    "home": "Algeria",
    "away": "Qatar",
    "homeELO": 1828.7,
    "awayELO": 1589.8,
    "expectedGoals": "2.15 - 0.68",
    "probability_1": 73.0,
    "probability_X": 18.7,
    "probability_2": 8.3,
    "confidence": 73.0,
    "prediction": "1",
    "prode": "1",
    "eloAdvantage": 2.389
  },
  {
    "home": "Germany",
    "away": "Saudi Arabia",
    "homeELO": 1878.7,
    "awayELO": 1690.8,
    "expectedGoals": "2.21 - 0.58",
    "probability_1": 72.9,
    "probability_X": 17.4,
    "probability_2": 9.7,
    "confidence": 72.9,
    "prediction": "1",
    "prode": "1",
    "eloAdvantage": 1.879
  },
  {
    "home": "Belgium",
    "away": "Haiti",
    "homeELO": 1804.6,
    "awayELO": 1673.3,
    "expectedGoals": "2.56 - 0.61",
    "probability_1": 72.9,
    "probability_X": 16.9,
    "probability_2": 10.2,
    "confidence": 72.9,
    "prediction": "1",
    "prode": "1",
    "eloAdvantage": 1.312
  },
  {
    "home": "Japan",
    "away": "Jordan",
    "homeELO": 1923.1,
    "awayELO": 1703.5,
    "expectedGoals": "2.06 - 0.64",
    "probability_1": 72.7,
    "probability_X": 18.4,
    "probability_2": 8.8,
    "confidence": 72.7,
    "prediction": "1",
    "prode": "1",
    "eloAdvantage": 2.196
  },
  {
    "home": "Netherlands",
    "away": "Ghana",
    "homeELO": 1866.5,
    "awayELO": 1633.3,
    "expectedGoals": "2.06 - 0.62",
    "probability_1": 72.7,
    "probability_X": 18.9,
    "probability_2": 8.4,
    "confidence": 72.7,
    "prediction": "1",
    "prode": "1",
    "eloAdvantage": 2.332
  },
  {
    "home": "Austria",
    "away": "Qatar",
    "homeELO": 1784.4,
    "awayELO": 1589.8,
    "expectedGoals": "2.23 - 0.56",
    "probability_1": 72.7,
    "probability_X": 18.6,
    "probability_2": 8.7,
    "confidence": 72.7,
    "prediction": "1",
    "prode": "1",
    "eloAdvantage": 1.945
  },
  {
    "home": "Brazil",
    "away": "Saudi Arabia",
    "homeELO": 1906.3,
    "awayELO": 1690.8,
    "expectedGoals": "1.98 - 0.49",
    "probability_1": 72.6,
    "probability_X": 19.0,
    "probability_2": 8.4,
    "confidence": 72.6,
    "prediction": "1",
    "prode": "1",
    "eloAdvantage": 2.155
  },
  {
    "home": "Mexico",
    "away": "Qatar",
    "homeELO": 1901.6,
    "awayELO": 1589.8,
    "expectedGoals": "1.93 - 0.54",
    "probability_1": 72.6,
    "probability_X": 20.2,
    "probability_2": 7.3,
    "confidence": 72.6,
    "prediction": "1",
    "prode": "1",
    "eloAdvantage": 3.118
  },
  {
    "home": "Netherlands",
    "away": "Iraq",
    "homeELO": 1866.5,
    "awayELO": 1687.5,
    "expectedGoals": "2.11 - 0.55",
    "probability_1": 72.6,
    "probability_X": 19.0,
    "probability_2": 8.4,
    "confidence": 72.6,
    "prediction": "1",
    "prode": "1",
    "eloAdvantage": 1.79
  },
  {
    "home": "Paraguay",
    "away": "Curaçao",
    "homeELO": 1700.9,
    "awayELO": 1597.2,
    "expectedGoals": "2.07 - 0.50",
    "probability_1": 72.4,
    "probability_X": 17.2,
    "probability_2": 10.4,
    "confidence": 72.4,
    "prediction": "1",
    "prode": "1",
    "eloAdvantage": 1.037
  },
  {
    "home": "Czech Republic",
    "away": "Curaçao",
    "homeELO": 1655.7,
    "awayELO": 1597.2,
    "expectedGoals": "2.41 - 0.68",
    "probability_1": 72.3,
    "probability_X": 15.5,
    "probability_2": 12.2,
    "confidence": 72.3,
    "prediction": "1",
    "prode": "1",
    "eloAdvantage": 0.586
  },
  {
    "home": "Spain",
    "away": "Uzbekistan",
    "homeELO": 2006.1,
    "awayELO": 1767.1,
    "expectedGoals": "1.84 - 0.45",
    "probability_1": 72.2,
    "probability_X": 20.8,
    "probability_2": 7.0,
    "confidence": 72.2,
    "prediction": "1",
    "prode": "1",
    "eloAdvantage": 2.39
  },
  {
    "home": "Morocco",
    "away": "Panama",
    "homeELO": 1950.5,
    "awayELO": 1746.6,
    "expectedGoals": "1.67 - 0.37",
    "probability_1": 72.2,
    "probability_X": 20.6,
    "probability_2": 7.2,
    "confidence": 72.2,
    "prediction": "1",
    "prode": "1",
    "eloAdvantage": 2.04
  },
  {
    "home": "Netherlands",
    "away": "South Africa",
    "homeELO": 1866.5,
    "awayELO": 1647.3,
    "expectedGoals": "2.17 - 0.60",
    "probability_1": 72.2,
    "probability_X": 19.4,
    "probability_2": 8.4,
    "confidence": 72.2,
    "prediction": "1",
    "prode": "1",
    "eloAdvantage": 2.191
  },
  {
    "home": "England",
    "away": "Sweden",
    "homeELO": 1969.7,
    "awayELO": 1701.6,
    "expectedGoals": "2.10 - 0.84",
    "probability_1": 72.1,
    "probability_X": 18.2,
    "probability_2": 9.7,
    "confidence": 72.1,
    "prediction": "1",
    "prode": "1",
    "eloAdvantage": 2.681
  },
  {
    "home": "Japan",
    "away": "New Zealand",
    "homeELO": 1923.1,
    "awayELO": 1685.3,
    "expectedGoals": "1.77 - 0.46",
    "probability_1": 72.0,
    "probability_X": 20.4,
    "probability_2": 7.6,
    "confidence": 72.0,
    "prediction": "1",
    "prode": "1",
    "eloAdvantage": 2.377
  },
  {
    "home": "Argentina",
    "away": "Paraguay",
    "homeELO": 2025.5,
    "awayELO": 1700.9,
    "expectedGoals": "1.50 - 0.36",
    "probability_1": 71.9,
    "probability_X": 22.1,
    "probability_2": 6.0,
    "confidence": 71.9,
    "prediction": "1",
    "prode": "1",
    "eloAdvantage": 3.246
  },
  {
    "home": "Brazil",
    "away": "Czech Republic",
    "homeELO": 1906.3,
    "awayELO": 1655.7,
    "expectedGoals": "2.10 - 0.79",
    "probability_1": 71.9,
    "probability_X": 18.1,
    "probability_2": 10.0,
    "confidence": 71.9,
    "prediction": "1",
    "prode": "1",
    "eloAdvantage": 2.506
  },
  {
    "home": "Germany",
    "away": "Czech Republic",
    "homeELO": 1878.7,
    "awayELO": 1655.7,
    "expectedGoals": "2.34 - 0.93",
    "probability_1": 71.9,
    "probability_X": 16.8,
    "probability_2": 11.3,
    "confidence": 71.9,
    "prediction": "1",
    "prode": "1",
    "eloAdvantage": 2.23
  },
  {
    "home": "Colombia",
    "away": "Saudi Arabia",
    "homeELO": 1919.9,
    "awayELO": 1690.8,
    "expectedGoals": "1.95 - 0.53",
    "probability_1": 71.7,
    "probability_X": 19.7,
    "probability_2": 8.5,
    "confidence": 71.7,
    "prediction": "1",
    "prode": "1",
    "eloAdvantage": 2.291
  },
  {
    "home": "Argentina",
    "away": "Turkey",
    "homeELO": 2025.5,
    "awayELO": 1770.6,
    "expectedGoals": "1.80 - 0.51",
    "probability_1": 71.6,
    "probability_X": 21.0,
    "probability_2": 7.3,
    "confidence": 71.6,
    "prediction": "1",
    "prode": "1",
    "eloAdvantage": 2.548
  },
  {
    "home": "Turkey",
    "away": "Qatar",
    "homeELO": 1770.6,
    "awayELO": 1589.8,
    "expectedGoals": "2.36 - 0.77",
    "probability_1": 71.4,
    "probability_X": 18.6,
    "probability_2": 10.0,
    "confidence": 71.4,
    "prediction": "1",
    "prode": "1",
    "eloAdvantage": 1.808
  },
  {
    "home": "Morocco",
    "away": "Tunisia",
    "homeELO": 1950.5,
    "awayELO": 1632.0,
    "expectedGoals": "1.36 - 0.37",
    "probability_1": 70.9,
    "probability_X": 22.9,
    "probability_2": 6.3,
    "confidence": 70.9,
    "prediction": "1",
    "prode": "1",
    "eloAdvantage": 3.185
  },
  {
    "home": "Portugal",
    "away": "Saudi Arabia",
    "homeELO": 1889.8,
    "awayELO": 1690.8,
    "expectedGoals": "1.96 - 0.51",
    "probability_1": 70.9,
    "probability_X": 20.5,
    "probability_2": 8.7,
    "confidence": 70.9,
    "prediction": "1",
    "prode": "1",
    "eloAdvantage": 1.99
  },
  {
    "home": "Morocco",
    "away": "New Zealand",
    "homeELO": 1950.5,
    "awayELO": 1685.3,
    "expectedGoals": "1.47 - 0.33",
    "probability_1": 70.8,
    "probability_X": 22.7,
    "probability_2": 6.6,
    "confidence": 70.8,
    "prediction": "1",
    "prode": "1",
    "eloAdvantage": 2.652
  },
  {
    "home": "Spain",
    "away": "Paraguay",
    "homeELO": 2006.1,
    "awayELO": 1700.9,
    "expectedGoals": "1.67 - 0.55",
    "probability_1": 70.7,
    "probability_X": 21.6,
    "probability_2": 7.6,
    "confidence": 70.7,
    "prediction": "1",
    "prode": "1",
    "eloAdvantage": 3.052
  },
  {
    "home": "Morocco",
    "away": "Ghana",
    "homeELO": 1950.5,
    "awayELO": 1633.3,
    "expectedGoals": "1.36 - 0.36",
    "probability_1": 70.7,
    "probability_X": 23.1,
    "probability_2": 6.3,
    "confidence": 70.7,
    "prediction": "1",
    "prode": "1",
    "eloAdvantage": 3.173
  },
  {
    "home": "France",
    "away": "Sweden",
    "homeELO": 1997.5,
    "awayELO": 1701.6,
    "expectedGoals": "2.20 - 1.02",
    "probability_1": 70.6,
    "probability_X": 17.9,
    "probability_2": 11.5,
    "confidence": 70.6,
    "prediction": "1",
    "prode": "1",
    "eloAdvantage": 2.959
  },
  {
    "home": "Morocco",
    "away": "Bosnia and Herzegovina",
    "homeELO": 1950.5,
    "awayELO": 1550.2,
    "expectedGoals": "1.38 - 0.37",
    "probability_1": 70.6,
    "probability_X": 23.4,
    "probability_2": 6.0,
    "confidence": 70.6,
    "prediction": "1",
    "prode": "1",
    "eloAdvantage": 4.003
  },
  {
    "home": "Iran",
    "away": "Qatar",
    "homeELO": 1852.0,
    "awayELO": 1589.8,
    "expectedGoals": "2.03 - 0.76",
    "probability_1": 70.6,
    "probability_X": 19.6,
    "probability_2": 9.8,
    "confidence": 70.6,
    "prediction": "1",
    "prode": "1",
    "eloAdvantage": 2.621
  },
  {
    "home": "Japan",
    "away": "Ghana",
    "homeELO": 1923.1,
    "awayELO": 1633.3,
    "expectedGoals": "1.64 - 0.51",
    "probability_1": 70.4,
    "probability_X": 21.7,
    "probability_2": 7.9,
    "confidence": 70.4,
    "prediction": "1",
    "prode": "1",
    "eloAdvantage": 2.898
  },
  {
    "home": "Japan",
    "away": "Tunisia",
    "homeELO": 1923.1,
    "awayELO": 1632.0,
    "expectedGoals": "1.64 - 0.53",
    "probability_1": 70.4,
    "probability_X": 21.7,
    "probability_2": 7.9,
    "confidence": 70.4,
    "prediction": "1",
    "prode": "1",
    "eloAdvantage": 2.911
  },
  {
    "home": "Japan",
    "away": "Iraq",
    "homeELO": 1923.1,
    "awayELO": 1687.5,
    "expectedGoals": "1.68 - 0.45",
    "probability_1": 70.3,
    "probability_X": 22.0,
    "probability_2": 7.7,
    "confidence": 70.3,
    "prediction": "1",
    "prode": "1",
    "eloAdvantage": 2.356
  },
  {
    "home": "Japan",
    "away": "Cabo Verde",
    "homeELO": 1923.1,
    "awayELO": 1639.3,
    "expectedGoals": "1.63 - 0.43",
    "probability_1": 70.3,
    "probability_X": 22.2,
    "probability_2": 7.4,
    "confidence": 70.3,
    "prediction": "1",
    "prode": "1",
    "eloAdvantage": 2.837
  },
  {
    "home": "Morocco",
    "away": "Cabo Verde",
    "homeELO": 1950.5,
    "awayELO": 1639.3,
    "expectedGoals": "1.35 - 0.31",
    "probability_1": 70.2,
    "probability_X": 23.8,
    "probability_2": 6.0,
    "confidence": 70.2,
    "prediction": "1",
    "prode": "1",
    "eloAdvantage": 3.112
  },
  {
    "home": "Belgium",
    "away": "Panama",
    "homeELO": 1804.6,
    "awayELO": 1746.6,
    "expectedGoals": "2.19 - 0.65",
    "probability_1": 70.2,
    "probability_X": 18.0,
    "probability_2": 11.8,
    "confidence": 70.2,
    "prediction": "1",
    "prode": "1",
    "eloAdvantage": 0.58
  },
  {
    "home": "Switzerland",
    "away": "Haiti",
    "homeELO": 1783.1,
    "awayELO": 1673.3,
    "expectedGoals": "2.39 - 0.61",
    "probability_1": 70.1,
    "probability_X": 18.5,
    "probability_2": 11.4,
    "confidence": 70.1,
    "prediction": "1",
    "prode": "1",
    "eloAdvantage": 1.098
  },
  {
    "home": "Portugal",
    "away": "Czech Republic",
    "homeELO": 1889.8,
    "awayELO": 1655.7,
    "expectedGoals": "2.08 - 0.82",
    "probability_1": 70.0,
    "probability_X": 19.4,
    "probability_2": 10.5,
    "confidence": 70.0,
    "prediction": "1",
    "prode": "1",
    "eloAdvantage": 2.341
  }
]